Workbook

Sheet Indice cap.4
A1: Capítulo 4
A2: PRODUCCIÓN, ÍNDICES DE PRECIOS Y POBLACIÓN
A4: PRODUCCIÓN
A6: 4.1 Oferta y Utilización Final de Bienes y Servicios / Miles de dólares de 2007
A7: 4.2 Oferta y Utilización Final de Bienes y Servicios/ Miles de dólares
A8: 4.3 Oferta y Utilización Final de Bienes y Servicios / Tasas de variación a Precios de 2007
A9: 4.4 Oferta y Utilización Final de Bienes y Servicios / Deflactores implícitos
A10: 4.5 Oferta y Utilización Final de Bienes y Servicios / Participación en el PIB - A precios de 2007
A11: 4.6 Oferta y Utilización Final de Bienes y Servicios / Contribución al crecimiento del PIB - A precios de 2007
A13: ÍNDICE DE PRECIOS
A15: 4.7 Indice Ponderado de Precios al Consumidor por Ciudades y por Categorías de Bienes y Servicios (1940-2014)
A16: 4.7.a Indice Ponderado de Precios al Consumidor por Ciudades y por Categorías de Bienes y Servicios (2015-2016)
... A49: Notas metodológicas de este capítulo

Sheet 4.1
A1: 4.1 OFERTA Y UTILIZACIÓN FINAL DE BIENES Y SERVICIOS
A2: Miles de dólares de 2007
A4: AÑOS | B4: Producto interno bruto (PIB) | C4: Importaciones de bienes y servicios | D4: Total oferta final | E4: Gasto de consumo final total | F4: Gobierno general | G4: Hogares residentes (*) | H4: Formación bruta de capital fijo | I4: Variación de existencias | J4: Exportaciones de bienes y servicios | K4: Total demanda final
A6: 1965 | B6: 10315274 | C6: 1663211 | D6: 11978485 | E6: 7756361 | F6: 1169835 | G6: 6586526 | H6: 2900959 | I6: 433141 | J6: 888024 | K6: 11978485
A7: 1966 | B7: 10280251 | C7: 1717049 | D7: 11997300 | E7: 7816797 | F7: 1183997 | G7: 6632800 | H7: 2932210 | I7: 326686 | J7: 921607 | K7: 11997300
A8: 1967 | B8: 10755309 | C8: 2069823 | D8: 12825132 | E8: 8108626 | F8: 1255248 | G8: 6853378 | H8: 3451557 | I8: 276198 | J8: 988751 | K8: 12825132
A9: 1968 | B9: 10960675 | C9: 2328028 | D9: 13288703 | E9: 8515648 | F9: 1336105 | G9: 7179543 | H9: 3654993 | I9: 103067 | J9: 1014995 | K9: 13288703
A10: 1969 | B10: 11472455 | C10: 2328566 | D10: 13801021 | E10: 9019510 | F10: 1448806 | G10: 7570704 | H10: 3764536 | I10: 125797 | J10: 891178 | K10: 13801021
A11: 1970 | B11: 12260834 | C11: 2403425 | D11: 14664259 | E11: 9723720 | F11: 1498394 | G11: 8225326 | H11: 3755199 | I11: 292490 | J11: 892850 | K11: 14664259
A12: 1971 | B12: 13032360 | C12: 2893429 | D12: 15925789 | E12: 10166640 | F12: 1514325 | G12: 8652315 | H12: 4696063 | I12: 76266 | J12: 986820 | K12: 15925789
A13: 1972 | B13: 13686277 | C13: 2727824 | D13: 16414101 | E13: 10012395 | F13: 1536926 | G13: 8475469 | H13: 4485935 | I13: 122234 | J13: 1793537 | K13: 16414101
A14: 1973 | B14: 15595606 | C14: 3226114 | D14: 18821720 | E14: 10634999 | F14: 1744447 | G14: 8890552 | H14: 4518591 | I14: -109630 | J14: 3777760 | K14: 18821720
A15: 1974 | B15: 17343641 | C15: 4740177 | D15: 22083818 | E15: 13216565 | F15: 2921326 | G15: 10295239 | H15: 4749379 | I15: -518379 | J15: 4636253 | K15: 22083818
A16: 1975 | B16: 19246612 | C16: 5001366 | D16: 24247978 | E16: 14810253 | F16: 3064627 | G16: 11745626 | H16: 5825874 | I16: -131068 | J16: 3742919 | K16: 24247978
A17: 1976 | B17: 20670320 | C17: 5100825 | D17: 25771145 | E17: 15979022 | F17: 3373336 | G17: 12605686 | H17: 6096519 | I17: -145812 | J17: 3841416 | K17: 25771145
... A54: 2013 | B54: 67546128 | C54: 20691563 | D54: 88237691 | E54: 51552041 | F54: 9609763 | G54: 41942278 | H54: 18214094 | I54: 261276 | J54: 18210280 | K54: 88237691
A55: 2014 sd | B55: 70243048 | C55: 21584147 | D55: 91827195 | E55: 53487685 | F55: 10111927 | G55: 43375758 | H55: 18904840 | I55: 460212 | J55: 18974458 | K55: 91827195
A56: 2015 p | B56: 70353852 | C56: 19731906 | D56: 90085758 | E56: 53485516 | F56: 10172307 | G56: 43313209 | H56: 17797927 | I56: -101688 | J56: 18904003 | K56: 90085758
A57: 2016 prel | B57: 69321410 | C57: 18462598 | D57: 87784008 | E57: 52341737 | F57: 9831775 | G57: 42509962 | H57: 16367027 | I57: 230738 | J57: 18844506 | K57: 87784008
A59: (*) Incluye Instituciones sin fines de lucro que sirven a los hogares
A60: sd: semidefinitivo
A61: p: provisional
A62: prel: preliminar por sumatoria de trimestres
A67: regresar al índice

Sheet 4.2
A1: 4.2 OFERTA Y UTILIZACIÓN FINAL DE BIENES Y SERVICIOS
A2: Miles de dólares
A4: AÑOS | B4: Producto interno bruto (PIB) | C4: Importaciones de bienes y servicios | D4: Total oferta final | E4: Gasto de consumo final total | F4: Gobierno general | G4: Hogares residentes (*) | H4: Formación bruta de capital fijo | I4: Variación de existencias | J4: Exportaciones de bienes y servicios | K4: Total demanda final
A6: 1965 | B6: 2385904 | C6: 245521 | D6: 2631425 | E6: 1835856 | F6: 225077 | G6: 1610779 | H6: 254420 | I6: 326903 | J6: 214246 | K6: 2631425
A7: 1966 | B7: 2428145 | C7: 269873 | D7: 2698018 | E7: 1899932 | F7: 222215 | G7: 1677717 | H7: 273737 | I7: 269741 | J7: 254608 | K7: 2698018
A8: 1967 | B8: 2552372 | C8: 307091 | D8: 2859463 | E8: 2016892 | F8: 190970 | G8: 1825922 | H8: 342052 | I8: 242546 | J8: 257973 | K8: 2859463
A9: 1968 | B9: 2580943 | C9: 359221 | D9: 2940164 | E9: 2181370 | F9: 185762 | G9: 1995608 | H9: 384334 | I9: 89468 | J9: 284992 | K9: 2940164
A10: 1969 | B10: 3110675 | C10: 376465 | D10: 3487140 | E10: 2523236 | F10: 256195 | G10: 2267041 | H10: 442828 | I10: 256577 | J10: 264499 | K10: 3487140
A11: 1970 | B11: 2861132 | C11: 372234 | D11: 3233366 | E11: 2403605 | F11: 277339 | G11: 2126266 | H11: 450556 | I11: 109079 | J11: 270126 | K11: 3233366
A12: 1971 | B12: 2752900 | C12: 459462 | D12: 3212362 | E12: 2304476 | F12: 234341 | G12: 2070135 | H12: 512330 | I12: 104288 | J12: 291268 | K12: 3212362
A13: 1972 | B13: 3184460 | C13: 495186 | D13: 3679646 | E13: 2544022 | F13: 293838 | G13: 2250184 | H13: 633048 | I13: 107451 | J13: 395125 | K13: 3679646
A14: 1973 | B14: 3889890 | C14: 648040 | D14: 4537930 | E14: 3044078 | F14: 420376 | G14: 2623702 | H14: 915277 | I14: -116861 | J14: 695436 | K14: 4537930
A15: 1974 | B15: 6596096 | C15: 1236921 | D15: 7833017 | E15: 4713377 | F15: 1057872 | G15: 3655505 | H15: 966016 | I15: 659473 | J15: 1494151 | K15: 7833017
A16: 1975 | B16: 7727971 | C16: 1494138 | D16: 9222109 | E16: 6390137 | F16: 1618152 | G16: 4771985 | H16: 1430749 | I16: 159269 | J16: 1241954 | K16: 9222109
A17: 1976 | B17: 9087566 | C17: 1633787 | D17: 10721353 | E17: 7350648 | F17: 1834862 | G17: 5515786 | H17: 1719679 | I17: 193777 | J17: 1457249 | K17: 10721353
... A54: 2013 | B54: 95129659 | C54: 29459627 | D54: 124589286 | E54: 70265165 | F54: 13323278 | G54: 56941887 | H54: 26211660 | I54: 868955 | J54: 27243506 | K54: 124589286
A55: 2014 sd | B55: 102292260 | C55: 30173593 | D55: 132465853 | E55: 74999440 | F55: 14442181 | G55: 60557259 | H55: 27702468 | I55: 1130848 | J55: 28633097 | K55: 132465853
A56: 2015 p | B56: 100176808 | C56: 23702545 | D56: 123879353 | E56: 76267509 | F56: 14402697 | G56: 61864812 | H56: 26359701 | I56: 541993 | J56: 20710150 | K56: 123879353
A57: 2016 prel | B57: 97802211 | C57: 19219016 | D57: 117021227 | E57: 75154200 | F57: 14025347 | G57: 61128853 | H57: 23026212 | I57: -44661 | J57: 18885476 | K57: 117021227
A59: (*) Incluye Instituciones sin fines de lucro que sirven a los hogares
A60: sd: semidefinitivo
A61: p: provisional
A62: prel: preliminar por sumatoria de trimestres
A67: regresar al índice

Sheet 4.3
A1: 4.3 OFERTA Y UTILIZACIÓN FINAL DE BIENES Y SERVICIOS
A2: Tasas de variación
A3: A precios de 2007
A5: AÑOS | B5: Producto interno bruto (PIB) | C5: Importaciones de bienes y servicios | D5: Total oferta final | E5: Gasto de consumo final total | F5: Gobierno general | G5: Hogares residentes (*) | H5: Formación bruta de capital fijo | I5: Exportaciones de bienes y servicios | J5: Total demanda final
A7: 1966 | B7: -0.33952564 | C7: 3.2369916 | D7: 0.15707329 | E7: 0.77917982 | F7: 1.2105981 | G7: 0.70255549 | H7: 1.0772644 | I7: 3.7817672 | J7: 0.15707329
A8: 1967 | B8: 4.6210739 | C8: 20.545366 | D8: 6.9001525 | E8: 3.7333578 | F8: 6.0178362 | G8: 3.3255639 | H8: 17.711794 | I8: 7.2855349 | J8: 6.9001525
A9: 1968 | B9: 1.9094384 | C9: 12.474738 | D9: 3.6145515 | E9: 5.0196174 | F9: 6.4415159 | G9: 4.7591859 | H9: 5.8940356 | I9: 2.6542577 | J9: 3.6145515
A10: 1969 | B10: 4.669238 | C10: 0.023109688 | D10: 3.8552897 | E10: 5.9168956 | F10: 8.4350407 | G10: 5.4482716 | H10: 2.9970782 | I10: -12.198779 | J10: 3.8552897
A11: 1970 | B11: 6.8719293 | C11: 3.2148112 | D11: 6.2548851 | E11: 7.8076303 | F11: 3.4226805 | G11: 8.6467784 | H11: -0.24802525 | I11: 0.18761684 | J11: 6.2548851
A12: 1971 | B12: 6.2926062 | C12: 20.387738 | D12: 8.6027531 | E12: 4.5550468 | F12: 1.063205 | G12: 5.1911499 | H12: 25.05497 | I12: 10.524724 | J12: 8.6027531
A13: 1972 | B13: 5.0176407 | C13: -5.7234859 | D13: 3.0661715 | E13: -1.5171679 | F13: 1.4924801 | G13: -2.0439154 | H13: -4.4745567 | I13: 81.749154 | J13: 3.0661715
A14: 1973 | B14: 13.950682 | C14: 18.266941 | D14: 14.667992 | E14: 6.2183324 | F14: 13.502342 | G14: 4.8974635 | H14: 0.72796418 | I14: 110.63184 | J14: 14.667992
A15: 1974 | B15: 11.20851 | C15: 46.931479 | D15: 17.331562 | E15: 24.274248 | F15: 67.464302 | G15: 15.799773 | H15: 5.1075213 | I15: 22.724922 | J15: 17.331562
A16: 1975 | B16: 10.972154 | C16: 5.5101107 | D16: 9.7997547 | E16: 12.058262 | F16: 4.9053409 | G16: 14.087939 | H16: 22.666016 | I16: -19.268448 | J16: 9.7997547
A17: 1976 | B17: 7.3971876 | C17: 1.9886367 | D17: 6.2816248 | E17: 7.8916208 | F17: 10.073298 | G17: 7.3223854 | H17: 4.6455691 | I17: 2.6315557 | J17: 6.2816248
A18: 1977 | B18: 1.6048421 | C18: 17.304926 | D18: 4.7123246 | E18: 3.846537 | F18: 4.329542 | G18: 3.7172828 | H18: 9.7791051 | I18: 1.476669 | J18: 4.7123246
... A54: 2013 | B54: 4.9465113 | C54: 6.9659671 | D54: 5.4131952 | E54: 5.0496605 | F54: 10.303736 | G54: 3.9155708 | H54: 10.414091 | I54: 2.5583551 | J54: 5.4131952
A55: 2014 sd | B55: 3.9927085 | C55: 4.3137582 | D55: 4.067994 | E55: 3.7547379 | F55: 5.2255607 | G55: 3.4177447 | H55: 3.7923709 | I55: 4.1964099 | J55: 4.067994
A56: 2015 p | B56: 0.15774372 | C56: -8.5814881 | D56: -1.8964284 | E56: -0.004055139 | F56: 0.59711665 | G56: -0.14420267 | H56: -5.8551831 | I56: -0.37131495 | J56: -1.8964284
A57: 2016 prel | B57: -1.4674989 | C57: -6.4327693 | D57: -2.5550654 | E57: -2.1384836 | F57: -3.3476379 | G57: -1.8545082 | H57: -8.0397004 | I57: -0.31473228 | J57: -2.5550654
A59: (*) Incluye Instituciones sin fines de lucro que sirven a los hogares
A60: sd: semidefinitivo
A61: p: provisional
A62: prel: preliminar por sumatoria de trimestres
A67: regresar al índice

Sheet 4.4
A1: 4.4 OFERTA Y UTILIZACIÓN FINAL DE BIENES Y SERVICIOS
A2: Deflactores implícitos
A3: 2007=100
A5: AÑOS | B5: Producto interno bruto (PIB) | C5: Importaciones de bienes y servicios | D5: Total oferta final | E5: Gasto de consumo final total | F5: Gobierno general | G5: Hogares residentes (*) | H5: Formación bruta de capital fijo | I5: Exportaciones de bienes y servicios | J5: Total demanda final
A7: 1965 | B7: 23.129817 | C7: 14.761867 | D7: 21.967928 | E7: 23.669038 | F7: 19.240064 | G7: 24.455669 | H7: 8.7702032 | I7: 24.12615 | J7: 21.967928
A8: 1966 | B8: 23.619511 | C8: 15.717257 | D8: 22.488543 | E8: 24.305761 | F8: 18.768206 | G8: 25.29425 | H8: 9.3355183 | I8: 27.626526 | J8: 22.488543
A9: 1967 | B9: 23.731275 | C9: 14.836583 | D9: 22.295778 | E9: 24.873413 | F9: 15.213727 | G9: 26.642657 | H9: 9.9100783 | I9: 26.090795 | J9: 22.295778
A10: 1968 | B10: 23.5473 | C10: 15.43027 | D10: 22.125289 | E10: 25.616019 | F10: 13.903249 | G10: 27.795752 | H10: 10.515314 | I10: 28.078168 | J10: 22.125289
A11: 1969 | B11: 27.114292 | C11: 16.167246 | D11: 25.267261 | E11: 27.975311 | F11: 17.683182 | G11: 29.944917 | H11: 11.76315 | I11: 29.679705 | J11: 25.267261
A12: 1970 | B12: 23.335541 | C12: 15.487648 | D12: 22.049297 | E12: 24.718986 | F12: 18.509084 | G12: 25.850234 | H12: 11.998192 | I12: 30.254354 | J12: 22.049297
A13: 1971 | B13: 21.123572 | C13: 15.879498 | D13: 20.170819 | E13: 22.667037 | F13: 15.474948 | G13: 23.925793 | H13: 10.909777 | I13: 29.515818 | J13: 20.170819
A14: 1972 | B14: 23.26754 | C14: 18.153151 | D14: 22.417591 | E14: 25.408726 | F14: 19.118552 | G14: 26.549374 | H14: 14.111841 | I14: 22.030491 | J14: 22.417591
A15: 1973 | B15: 24.942218 | C15: 20.087325 | D15: 24.110071 | E15: 28.623209 | F15: 24.097952 | G15: 29.511126 | H15: 20.255805 | I15: 18.408687 | J15: 24.110071
A16: 1974 | B16: 38.031784 | C16: 26.094405 | D16: 35.469487 | E16: 35.662648 | F16: 36.212049 | G16: 35.506752 | H16: 20.339838 | I16: 32.227555 | J16: 35.469487
A17: 1975 | B17: 40.152371 | C17: 29.874598 | D17: 38.032487 | E17: 43.146711 | F17: 52.800944 | G17: 40.627762 | H17: 24.55853 | I17: 33.181429 | J17: 38.032487
A18: 1976 | B18: 43.964322 | C18: 32.029858 | D18: 41.60216 | E18: 46.001864 | F18: 54.393099 | G18: 43.756333 | H18: 28.207556 | I18: 37.935204 | J18: 41.60216
... A47: 2005 | B47: 86.81798 | C47: 88.848246 | D47: 87.260001 | E47: 92.360607 | F47: 87.548191 | G47: 93.161762 | H47: 87.12879 | I47: 75.409744 | J47: 87.260001
A48: 2006 | B48: =+('[1]4.2'!B47/'[1]4.1'!B47)*100 -> 93.764209 | C48: =+('[1]4.2'!C47/'[1]4.1'!C47)*100 -> 94.130807 | D48: =+('[1]4.2'!D47/'[1]4.1'!D47)*100 -> 93.847199 | E48: =+('[1]4.2'!E47/'[1]4.1'!E47)*100 -> 96.544254 | F48: =+('[1]4.2'!F47/'[1]4.1'!F47)*100 -> 94.078209 | G48: =+('[1]4.2'!G47/'[1]4.1'!G47)*100 -> 96.952602 | H48: =+('[1]4.2'!H47/'[1]4.1'!H47)*100 -> 95.554003 | I48: =+('[1]4.2'!J47/'[1]4.1'!J47)*100 -> 87.17594 | J48: =+('[1]4.2'!K47/'[1]4.1'!K47)*100 -> 93.847199
A49: 2007 | B49: =+('[1]4.2'!B48/'[1]4.1'!B48)*100 -> 100 | C49: =+('[1]4.2'!C48/'[1]4.1'!C48)*100 -> 100 | D49: =+('[1]4.2'!D48/'[1]4.1'!D48)*100 -> 100 | E49: =+('[1]4.2'!E48/'[1]4.1'!E48)*100 -> 100 | F49: =+('[1]4.2'!F48/'[1]4.1'!F48)*100 -> 100 | G49: =+('[1]4.2'!G48/'[1]4.1'!G48)*100 -> 100 | H49: =+('[1]4.2'!H48/'[1]4.1'!H48)*100 -> 100 | I49: =+('[1]4.2'!J48/'[1]4.1'!J48)*100 -> 100 | J49: =+('[1]4.2'!K48/'[1]4.1'!K48)*100 -> 100
A50: 2008 | B50: =+('[1]4.2'!B49/'[1]4.1'!B49)*100 -> 113.84732 | C50: =+('[1]4.2'!C49/'[1]4.1'!C49)*100 -> 116.98278 | D50: =+('[1]4.2'!D49/'[1]4.1'!D49)*100 -> 114.62502 | E50: =+('[1]4.2'!E49/'[1]4.1'!E49)*100 -> 109.98355 | F50: =+('[1]4.2'!F49/'[1]4.1'!F49)*100 -> 118.01611 | G50: =+('[1]4.2'!G49/'[1]4.1'!G49)*100 -> 108.56242 | H50: =+('[1]4.2'!H49/'[1]4.1'!H49)*100 -> 112.47169 | I50: =+('[1]4.2'!J49/'[1]4.1'!J49)*100 -> 125.79433 | J50: =+('[1]4.2'!K49/'[1]4.1'!K49)*100 -> 114.62502
A51: 2009 | B51: =+('[1]4.2'!B50/'[1]4.1'!B50)*100 -> 114.59363 | C51: =+('[1]4.2'!C50/'[1]4.1'!C50)*100 -> 104.1608 | D51: =+('[1]4.2'!D50/'[1]4.1'!D50)*100 -> 112.2142 | E51: =+('[1]4.2'!E50/'[1]4.1'!E50)*100 -> 114.28321 | F51: =+('[1]4.2'!F50/'[1]4.1'!F50)*100 -> 124.18176 | G51: =+('[1]4.2'!G50/'[1]4.1'!G50)*100 -> 112.30905 | H51: =+('[1]4.2'!H50/'[1]4.1'!H50)*100 -> 120.38582 | I51: =+('[1]4.2'!J50/'[1]4.1'!J50)*100 -> 98.842523 | J51: =+('[1]4.2'!K50/'[1]4.1'!K50)*100 -> 112.2142
A52: 2010 | B52: =+('[1]4.2'!B51/'[1]4.1'!B51)*100 -> 123.14814 | C52: =+('[1]4.2'!C51/'[1]4.1'!C51)*100 -> 121.78786 | D52: =+('[1]4.2'!D51/'[1]4.1'!D51)*100 -> 122.81239 | E52: =+('[1]4.2'!E51/'[1]4.1'!E51)*100 -> 119.44358 | F52: =+('[1]4.2'!F51/'[1]4.1'!F51)*100 -> 127.27609 | G52: =+('[1]4.2'!G51/'[1]4.1'!G51)*100 -> 117.92968 | H52: =+('[1]4.2'!H51/'[1]4.1'!H51)*100 -> 131.2467 | I52: =+('[1]4.2'!J51/'[1]4.1'!J51)*100 -> 121.7778 | J52: =+('[1]4.2'!K51/'[1]4.1'!K51)*100 -> 122.81239
A53: 2011 | B53: =+('[1]4.2'!B52/'[1]4.1'!B52)*100 -> 130.12159 | C53: =+('[1]4.2'!C52/'[1]4.1'!C52)*100 -> 137.89614 | D53: =+('[1]4.2'!D52/'[1]4.1'!D52)*100 -> 131.98338 | E53: =+('[1]4.2'!E52/'[1]4.1'!E52)*100 -> 124.79593 | F53: =+('[1]4.2'!F52/'[1]4.1'!F52)*100 -> 128.69937 | G53: =+('[1]4.2'!G52/'[1]4.1'!G52)*100 -> 124.01584 | H53: =+('[1]4.2'!H52/'[1]4.1'!H52)*100 -> 137.19639 | I53: =+('[1]4.2'!J52/'[1]4.1'!J52)*100 -> 146.54499 | J53: =+('[1]4.2'!K52/'[1]4.1'!K52)*100 -> 131.98338
A54: 2012 | B54: =+('[1]4.2'!B53/'[1]4.1'!B53)*100 -> 136.60848 | C54: =+('[1]4.2'!C53/'[1]4.1'!C53)*100 -> 143.56919 | D54: =+('[1]4.2'!D53/'[1]4.1'!D53)*100 -> 138.21706 | E54: =+('[1]4.2'!E53/'[1]4.1'!E53)*100 -> 131.91315 | F54: =+('[1]4.2'!F53/'[1]4.1'!F53)*100 -> 134.60317 | G54: =+('[1]4.2'!G53/'[1]4.1'!G53)*100 -> 131.33251 | H54: =+('[1]4.2'!H53/'[1]4.1'!H53)*100 -> 143.71724 | I54: =+('[1]4.2'!J53/'[1]4.1'!J53)*100 -> 149.3706 | J54: =+('[1]4.2'!K53/'[1]4.1'!K53)*100 -> 138.21706
A55: 2013 | B55: =+('[1]4.2'!B54/'[1]4.1'!B54)*100 -> 140.83658 | C55: =+('[1]4.2'!C54/'[1]4.1'!C54)*100 -> 142.37507 | D55: =+('[1]4.2'!D54/'[1]4.1'!D54)*100 -> 141.19736 | E55: =+('[1]4.2'!E54/'[1]4.1'!E54)*100 -> 136.29948 | F55: =+('[1]4.2'!F54/'[1]4.1'!F54)*100 -> 138.64315 | G55: =+('[1]4.2'!G54/'[1]4.1'!G54)*100 -> 135.7625 | H55: =+('[1]4.2'!H54/'[1]4.1'!H54)*100 -> 143.90867 | I55: =+('[1]4.2'!J54/'[1]4.1'!J54)*100 -> 149.60509 | J55: =+('[1]4.2'!K54/'[1]4.1'!K54)*100 -> 141.19736
A56: 2014 sd | B56: =+('[1]4.2'!B55/'[1]4.1'!B55)*100 -> 145.62617 | C56: =+('[1]4.2'!C55/'[1]4.1'!C55)*100 -> 139.79516 | D56: =+('[1]4.2'!D55/'[1]4.1'!D55)*100 -> 144.25558 | E56: =+('[1]4.2'!E55/'[1]4.1'!E55)*100 -> 140.21815 | F56: =+('[1]4.2'!F55/'[1]4.1'!F55)*100 -> 142.82323 | G56: =+('[1]4.2'!G55/'[1]4.1'!G55)*100 -> 139.61084 | H56: =+('[1]4.2'!H55/'[1]4.1'!H55)*100 -> 146.53638 | I56: =+('[1]4.2'!J55/'[1]4.1'!J55)*100 -> 150.90337 | J56: =+('[1]4.2'!K55/'[1]4.1'!K55)*100 -> 144.25558
A57: 2015 p | B57: =+('[1]4.2'!B56/'[1]4.1'!B56)*100 -> 142.38994 | C57: =+('[1]4.2'!C56/'[1]4.1'!C56)*100 -> 120.12294 | D57: =+('[1]4.2'!D56/'[1]4.1'!D56)*100 -> 137.51269 | E57: =+('[1]4.2'!E56/'[1]4.1'!E56)*100 -> 142.5947 | F57: =+('[1]4.2'!F56/'[1]4.1'!F56)*100 -> 141.58732 | G57: =+('[1]4.2'!G56/'[1]4.1'!G56)*100 -> 142.83128 | H57: =+('[1]4.2'!H56/'[1]4.1'!H56)*100 -> 148.10546 | I57: =+('[1]4.2'!J56/'[1]4.1'!J56)*100 -> 109.55431 | J57: =+('[1]4.2'!K56/'[1]4.1'!K56)*100 -> 137.51269
A58: 2016 prel | B58: =+('[1]4.2'!B57/'[1]4.1'!B57)*100 -> 141.08514 | C58: =+('[1]4.2'!C57/'[1]4.1'!C57)*100 -> 104.09703 | D58: =+('[1]4.2'!D57/'[1]4.1'!D57)*100 -> 133.30586 | E58: =+('[1]4.2'!E57/'[1]4.1'!E57)*100 -> 143.58369 | F58: =+('[1]4.2'!F57/'[1]4.1'!F57)*100 -> 142.65325 | G58: =+('[1]4.2'!G57/'[1]4.1'!G57)*100 -> 143.79889 | H58: =+('[1]4.2'!H57/'[1]4.1'!H57)*100 -> 140.68659 | I58: =+('[1]4.2'!J57/'[1]4.1'!J57)*100 -> 100.21741 | J58: =+('[1]4.2'!K57/'[1]4.1'!K57)*100 -> 133.30586
A60: (*) Incluye Instituciones sin fines de lucro que sirven a los hogares
A61: sd: semidefinitivo
A62: p: provisional
A63: prel: preliminar por sumatoria de trimestres
A68: regresar al índice

Sheet 4.5
A1: 4.5 OFERTA Y UTILIZACIÓN FINAL DE BIENES Y SERVICIOS
A2: Participación en el PIB
A3: A precios de 2007
A5: AÑOS | B5: Producto interno bruto (PIB) | C5: Importaciones de bienes y servicios | D5: Gasto de consumo final total | E5: Gobierno general | F5: Hogares residentes(*) | G5: Formación bruta de capital fijo | H5: Variación de existencias | I5: Exportaciones de bienes y servicios
A7: 1965 | B7: 100 | C7: 16.123769 | D7: 75.192971 | E7: 11.340804 | F7: 63.852167 | G7: 28.122947 | H7: 4.1990256 | I7: 8.6088261
A8: 1966 | B8: 100 | C8: 16.702403 | D8: 76.037025 | E8: 11.517199 | F8: 64.519825 | G8: 28.522747 | H8: 3.1778018 | I8: 8.9648297
A9: 1967 | B9: 100 | C9: 19.244663 | D9: 75.391846 | E9: 11.670962 | F9: 63.720884 | G9: 32.091658 | H9: 2.5680155 | I9: 9.1931436
A10: 1968 | B10: 100 | C10: 21.239823 | D10: 77.692733 | E10: 12.189988 | F10: 65.502745 | G10: 33.346423 | H10: 0.94033442 | I10: 9.260333
A11: 1969 | B11: 100 | C11: 20.297016 | D11: 78.618831 | E11: 12.628561 | F11: 65.99027 | G11: 32.813692 | H11: 1.0965133 | I11: 7.7679799
A12: 1970 | B12: 100 | C12: 19.602459 | D12: 79.307166 | E12: 12.220979 | F12: 67.086187 | G12: 30.627598 | H12: 2.3855637 | I12: 7.2821311
A13: 1971 | B13: 100 | C13: 22.201881 | D13: 78.010736 | E13: 11.61973 | F13: 66.391007 | G13: 36.033865 | H13: 0.58520483 | I13: 7.5720744
A14: 1972 | B14: 100 | C14: 19.931089 | D14: 73.156454 | E14: 11.229686 | F14: 61.926768 | G14: 32.776883 | H14: 0.89311359 | I14: 13.104638
A15: 1973 | B15: 100 | C15: 20.686045 | D15: 68.192278 | E15: 11.185503 | F15: 57.006775 | G15: 28.973488 | H15: -0.70295441 | I15: 24.223233
A16: 1974 | B16: 100 | C16: 27.330922 | D16: 76.204097 | E16: 16.843787 | F16: 59.36031 | G16: 27.383979 | H16: -2.9888707 | I16: 26.731717
A17: 1975 | B17: 100 | C17: 25.985696 | D17: 76.949922 | E17: 15.922943 | F17: 61.02698 | G17: 30.269608 | H17: -0.68099258 | I17: 19.447158
A18: 1976 | B18: 100 | C18: 24.677049 | D18: 77.304183 | E18: 16.319709 | F18: 60.984474 | G18: 29.494072 | H18: -0.70541724 | I18: 18.584212
... A55: 2013 | B55: 100 | C55: 30.633233 | D55: 76.321238 | E55: 14.226964 | F55: 62.094274 | G55: 26.965415 | H55: 0.38681122 | I55: 26.959769
A56: 2014 sd | B56: 100 | C56: 30.727805 | D56: 76.146589 | E56: 14.395627 | F56: 61.750962 | G56: 26.913468 | H56: 0.65517089 | I56: 27.012578
A57: 2015 p | B57: 100 | C57: 28.04666 | D57: 76.023579 | E57: 14.458778 | F57: 61.564801 | G57: 25.297729 | H57: -0.14453793 | I57: 26.869891
A58: 2016 prel | B58: 100 | C58: 26.633327 | D58: 75.505875 | E58: 14.182884 | F58: 61.322991 | G58: 23.610349 | H58: 0.33285243 | I58: 27.184251
A60: (*) Incluye Instituciones sin fines de lucro que sirven a los hogares
A61: sd: semidefinitivo
A62: p: provisional
A63: prel: preliminar por sumatoria de trimestres
A68: regresar al índice

Sheet 4.6
A1: 4.6 OFERTA Y UTILIZACIÓN FINAL DE BIENES Y SERVICIOS
A2: Contribución al crecimiento del PIB
A3: A precios de 2007
A5: AÑOS | B5: Producto interno bruto (PIB) | C5: Importaciones de bienes y servicios | D5: Gobierno general | E5: Hogares residentes(*) | F5: Formación bruta de capital fijo | G5: Variación de existencias | H5: Exportaciones de bienes y servicios
A7: 1966 | B7: -0.33952564 | C7: 0.52192506 | D7: 0.13729155 | E7: 0.44859691 | F7: 0.30295851 | G7: -1.0320133 | H7: 0.32556576
A8: 1967 | B8: 4.6210739 | C8: 3.4315699 | D8: 0.69308619 | E8: 2.145648 | F8: 5.0518903 | G8: -0.49111641 | H8: 0.6531358
A9: 1968 | B9: 1.9094384 | C9: 2.4007214 | D9: 0.75178686 | E9: 3.0325953 | F9: 1.8914938 | G9: -1.609726 | H9: 0.24400973
A10: 1969 | B10: 4.669238 | C10: 0.0049084568 | D10: 1.0282305 | E10: 3.5687674 | F10: 0.99941838 | G10: 0.20737774 | H10: -1.1296476
A11: 1970 | B11: 6.8719293 | C11: 0.65251073 | D11: 0.4322353 | E11: 5.7060324 | F11: -0.081386242 | G11: 1.4529846 | H11: 0.014574038
A12: 1971 | B12: 6.2926062 | C12: 3.9964981 | D12: 0.12993406 | E12: 3.4825445 | F12: 7.6737357 | G12: -1.7635342 | H12: 0.76642421
A13: 1972 | B13: 5.0176407 | C13: -1.2707215 | D13: 0.17342216 | E13: -1.356976 | F13: -1.6123557 | G13: 0.35272199 | H13: 6.1901068
A14: 1973 | B14: 13.950682 | C14: 3.6408002 | D14: 1.5162706 | E14: 3.0328409 | F14: 0.23860397 | G14: -1.6941349 | H14: 14.497902
A15: 1974 | B15: 11.20851 | C15: 9.7082665 | D15: 7.5462217 | E15: 9.0069408 | F15: 1.4798271 | G15: -2.6209241 | H15: 5.5047107
A16: 1975 | B16: 10.972154 | C16: 1.5059641 | D16: 0.82624519 | E16: 8.3626443 | F16: 6.206857 | G16: 2.2331585 | H16: -5.150787
A17: 1976 | B17: 7.3971876 | C17: 0.51676108 | D17: 1.6039654 | E17: 4.4686306 | F17: 1.4061955 | G17: -0.07660569 | H17: 0.5117628
A18: 1977 | B18: 1.6048421 | C18: 4.2703451 | D18: 0.70656865 | E18: 2.2669654 | F18: 2.8842563 | G18: -0.25703037 | H18: 0.27442729
... A47: 2006 | B47: 4.4035264 | C47: 2.7200492 | D47: 0.40335651 | E47: 2.7785211 | F47: 1.0140826 | G47: 0.66180821 | H47: 2.2658072
A48: 2007 | B48: =+'[1]4.5'!B49*'[1]4.3'!B48/100 -> 2.190064 | C48: 2.0644435 | D48: 0.60098029 | E48: 2.7041078 | F48: 0.76155851 | G48: 0.18224522 | H48: 0.0056155897
A49: 2008 | B49: 6.3571306 | C49: 4.4263936 | D49: 1.209892 | E49: 3.5162834 | F49: 3.3176666 | G49: 1.786855 | H49: 0.95282725
A50: 2009 | B50: 0.56649159 | C50: -3.2718648 | D50: 1.3251624 | E50: -0.63863114 | F50: -0.81637358 | G50: -1.0950203 | H50: -1.4805105
A51: 2010 | B51: 3.5252987 | C51: 4.3798741 | D51: 0.55583506 | E51: 4.8980024 | F51: 2.2120036 | G51: 0.30872801 | H51: -0.069396213
A52: 2011 | B52: 7.8681409 | C52: 1.1949405 | D52: 1.1107742 | E52: 3.3887363 | F52: 3.3119831 | G52: -0.34722262 | H52: 1.5988104
A53: 2012 | B53: 5.6419621 | C53: 0.26287867 | D53: 1.4299698 | E53: 1.8502254 | F53: 2.5857617 | G53: -1.4717194 | H53: 1.5106033
A54: 2013 | B54: 4.9465113 | C54: 2.0936141 | D54: 1.3947127 | E54: 2.4554665 | F54: 2.669144 | G54: -0.18498524 | H54: 0.70578749
A55: 2014 sd | B55: 3.9927085 | C55: 1.3214436 | D55: 0.74343862 | E55: 2.1222238 | F55: 1.0226286 | G55: 0.29451873 | H55: 1.1313424
A56: 2015 p | B56: 0.15774372 | C56: -2.6369029 | D56: 0.085958684 | E56: -0.089046535 | F56: -1.5758328 | G56: -0.79993681 | H56: -0.10030174
A57: 2016 prel | B57: -1.4674989 | C57: -1.804177 | D57: -0.48402751 | E57: -1.1417243 | F57: -2.0338616 | G57: 0.47250576 | H57: -0.08456822
A59: (*) Incluye Instituciones sin fines de lucro que sirven a los hogares
A60: sd: semidefinitivo
A61: p: provisional
A62: prel: preliminar por sumatoria de trimestres
A67: regresar al índice

Sheet 4.7
A1: 4.7 ÍNDICE PONDERADO DE PRECIOS AL CONSUMIDOR POR CIUDADES Y POR CATEGORÍAS DE BIENES Y SERVICIOS (1940-2014) (1)
A2: (Familias de ingresos bajos, medios y altos de Quito, Guayaquil y Cuenca) (2)
A3: Base: enero - diciembre de 2004 = 100
A5: Año | C5: Indice Nacional | D5: Por ciudades | G5: Por grupo de bienes y servicios
D6: Quito | E6: Guayaquil | F6: Cuenca | G6: Alimentos | H6: Vivienda | I6: Indumentaria | J6: Diversos
A8: 1940 | C8: 0.0034368997 | D8: 0.0038048745
A9: 1941 | C9: 0.0035546017 | D9: 0.0039351784
A10: 1942 | C10: 0.0045668393 | D10: 0.0050557921
A11: 1943 | C11: 0.0055790769 | D11: 0.0061764058
A12: 1944 | C12: 0.0068502589 | D12: 0.0075836881
A13: 1945 | C13: 0.0088982745 | D13: 0.0098509763
A14: 1946 | C14: 0.010216537 | D14: 0.01131038
A15: 1947 | C15: 0.011676043 | D15: 0.012926149
A16: 1948 | C16: 0.013064927 | D16: 0.014463735
A17: 1949 | C17: 0.012829523 | D17: 0.014203127
A18: 1950 | C18: 0.012758901 | D18: 0.013994641 | G18: 0.01005001 | H18: 0.021469681 | I18: 0.027489974 | J18: 0.012542512
A19: 1951 | C19: 0.014265488 | D19: 0.015792835 | G19: 0.0099265889 | H19: 0.031203224 | I19: 0.029872121 | J19: 0.015372502
A20: 1952 | C20: 0.014736296 | D20: 0.016314051 | G20: 0.010296852 | H20: 0.031715515 | I20: 0.030300908 | J20: 0.015621541
A21: 1953 | C21: 0.014806917 | D21: 0.016392233 | G21: 0.010226326 | H21: 0.032600383 | I21: 0.030634408 | J21: 0.0158253
A22: 1954 | C22: 0.015348346 | D22: 0.016991631 | G22: 0.010878695 | H22: 0.032227807 | I22: 0.031253766 | J22: 0.0158253
A23: 1955 | C23: 0.016054559 | D23: 0.017226178 | E23: 0.018106428 | G23: 0.01214817 | H23: 0.029852636 | I23: 0.034779344 | J23: 0.016391298
A24: 1956 | C24: 0.015583751 | D24: 0.016418294 | E24: 0.017820674 | G24: 0.011566327 | H24: 0.0304115 | I24: 0.032492483 | J24: 0.015598901
A25: 1957 | C25: 0.015748533 | D25: 0.016522537 | E25: 0.018028495 | G25: 0.011760275 | H25: 0.030737504 | I25: 0.032206625 | J25: 0.015168742
A26: 1958 | C26: 0.015913316 | D26: 0.016809206 | E26: 0.018158384 | G26: 0.01181317 | H26: 0.030970364 | I26: 0.032206625 | J26: 0.016096979
A27: 1959 | C27: 0.015866235 | D27: 0.016835266 | E27: 0.018054473 | G27: 0.011513433 | H27: 0.032041519 | I27: 0.033111841 | J27: 0.016210178
A28: 1960 | C28: 0.015960397 | D28: 0.017069813 | E28: 0.018028495 | G28: 0.011390011 | H28: 0.033298963 | I28: 0.033064198 | J28: 0.016459217
A29: 1961 | C29: 0.016760771 | D29: 0.017799515 | E29: 0.019041624 | G29: 0.012130539 | H29: 0.034556406 | I29: 0.035779845 | J29: 0.016866736
A30: 1962 | C30: 0.017043256 | D30: 0.01829467 | E30: 0.019223468 | G30: 0.01214817 | H30: 0.036186425 | I30: 0.037542634 | J30: 0.017342174
A31: 1963 | C31: 0.017561145 | D31: 0.019389223 | E31: 0.019405311 | G31: 0.01258896 | H31: 0.036885005 | I31: 0.038114349 | J31: 0.018949608
A32: 1964 | C32: 0.017796549 | D32: 0.020040743 | E32: 0.02008073 | G32: 0.013012118 | H32: 0.038328736 | I32: 0.036494489 | J32: 0.017862892
A33: 1965 | C33: 0.018926489 | D33: 0.020692262 | E33: 0.021093859 | G33: 0.013629224 | H33: 0.039958755 | I33: 0.038733707 | J33: 0.01854209
A34: 1966 | C34: 0.019632701 | D34: 0.021526208 | E34: 0.021795256 | G34: 0.014299225 | H34: 0.041076482 | I34: 0.040353567 | J34: 0.019357126
... A36: 1968 | C36: 0.021186368 | D36: 0.023298341 | E36: 0.023483804 | G36: 0.015797911 | H36: 0.042706502 | I36: 0.040687068 | J36: 0.02094192
A37: 1969 | C37: 0.022292767 | D37: 0.024809866 | E37: 0.024600843 | F37: 0.01565664 | G37: 0.017032122 | H37: 0.043451653 | I37: 0.043259786 | J37: 0.021304159
A38: 1970 | C38: 0.023540409 | D38: 0.026060784 | E38: 0.025977659 | F38: 0.016944416 | G38: 0.017631597 | H38: 0.046571976 | I38: 0.047642937 | J38: 0.022639914
A39: 1971 | C39: 0.025776747 | D39: 0.02824989 | E39: 0.028523469 | F39: 0.019181079 | G39: 0.019006861 | H39: 0.051694893 | I39: 0.053836518 | J39: 0.024858625
A40: 1972 | C40: 0.027754142 | D40: 0.030491117 | E40: 0.030653637 | F40: 0.02060441 | G40: 0.020946337 | H40: 0.054815215 | I40: 0.057457381 | J40: 0.025673662
A41: 1973 | C41: 0.031073339 | D41: 0.034426296 | E41: 0.034212577 | F41: 0.022688573 | G41: 0.024560814 | H41: 0.057935538 | I41: 0.063555677 | J41: 0.027484856
A42: 1974 | C42: 0.038135462 | D42: 0.042479078 | E42: 0.041798053 | F42: 0.027958286 | G42: 0.032212927 | H42: 0.064874762 | I42: 0.076943343 | J42: 0.030835563
A43: 1975 | C43: 0.043997024 | D43: 0.048994274 | E43: 0.047435205 | F43: 0.032313001 | G43: 0.037925564 | H43: 0.075027453 | I43: 0.089187577 | J43: 0.032895795
A44: 1976 | C44: 0.048634484 | D44: 0.054232491 | E44: 0.052059228 | F44: 0.035549384 | G44: 0.041681094 | H44: 0.084202132 | I44: 0.099478452 | J44: 0.036133303
A45: 1977 | C45: 0.054919773 | D45: 0.061294964 | E45: 0.058943308 | F45: 0.039311044 | G45: 0.047746364 | H45: 0.095379406 | I45: 0.11248497 | J45: 0.03939345
A46: 1978 | C46: 0.062382083 | D46: 0.068696226 | E46: 0.067100293 | F46: 0.045156868 | G46: 0.05377637 | H46: 0.10958386 | I46: 0.12487214 | J46: 0.045891106
A47: 1979 | C47: 0.068690912 | D47: 0.07547203 | E47: 0.073776551 | F47: 0.050392692 | G47: 0.058960059 | H47: 0.12038856 | I47: 0.13540123 | J47: 0.052071802
A48: 1980 | C48: 0.077353783 | D48: 0.085296946 | E48: 0.082816776 | F48: 0.058017679 | G48: 0.064743223 | H48: 0.1400885 | I48: 0.15993734 | J48: 0.059316574
A49: 1981 | B49: -3 | C49: 0.088747341 | D49: 0.099291587 | E49: 0.093675438 | F49: 0.06872655 | G49: 0.073294547 | H49: 0.16188419 | I49: 0.18537867 | J49: 0.069821495
A50: 1982 | C50: 0.1032447 | D50: 0.11183592 | E50: 0.10761235 | F50: 0.084745521 | G50: 0.085854784 | H50: 0.18650536 | I50: 0.214791 | J50: 0.08145841
A51: 1983 | C51: 0.15320181 | D51: 0.16236761 | E51: 0.16176521 | F51: 0.12599085 | G51: 0.15273672 | H51: 0.22405264 | I51: 0.27968703 | J51: 0.11032001
A52: 1984 | C52: 0.20100391 | D52: 0.20978094 | E52: 0.21127243 | F52: 0.17000778 | G52: 0.20923129 | H52: 0.27501846 | I52: 0.36050349 | J52: 0.13995057
A53: 1985 | C53: 0.25729545 | D53: 0.27016383 | E53: 0.26916954 | F53: 0.21797074 | G53: 0.27346339 | H53: 0.31650513 | I53: 0.4558912 | J53: 0.18619065
A54: 1986 | C54: 0.31652565 | D54: 0.33083021 | E54: 0.33198963 | F54: 0.27025553 | G54: 0.33690053 | H54: 0.37116412 | I54: 0.58797688 | J54: 0.23222568
A55: 1987 | C55: 0.40990953 | D55: 0.42402681 | E55: 0.43911662 | F55: 0.34654529 | G55: 0.43372565 | H55: 0.46600487 | I55: 0.74569715 | J55: 0.31265881
A56: 1988 | C56: 0.64859352 | D56: 0.66123519 | E56: 0.70156038 | F56: 0.53261902 | G56: 0.7127537 | H56: 0.64692122 | I56: 1.155581 | J56: 0.49582489
A57: 1989 | C57: 1.1391528 | D57: 1.1438022 | E57: 1.2353925 | F57: 0.9605745 | G57: 1.3397056 | H57: 0.96305703 | I57: 1.9283969 | J57: 0.8241192
A58: 1990 | C58: 1.6918809 | D58: 1.6559229 | E58: 1.8572837 | F58: 1.4077434 | G58: 1.9763559 | H58: 1.4115316 | I58: 2.8365364 | J58: 1.2567869
A59: 1991 | C59: 2.5162059 | D59: 2.4164496 | E59: 2.7832214 | F59: 2.086647 | G59: 2.9370286 | H59: 2.0467578 | I59: 4.2807091 | J59: 1.8770294
A60: 1992 | C60: 3.8902006 | D60: 3.7912235 | E60: 4.2845939 | F60: 3.1403289 | G60: 4.5239112 | H60: 3.0115383 | I60: 6.3124539 | J60: 3.0269822
A61: 1993 | C61: 5.6390424 | D61: 5.6256728 | E61: 6.1283567 | F61: 4.5790767 | G61: 6.4163732 | H61: 4.3947556 | I61: 8.758265 | J61: 4.6687614
... A63: 1995 | C63: 8.8255606 | D63: 9.0889718 | E63: 9.5370748 | F63: 7.0868676 | G63: 9.6925282 | H63: 7.1161334 | I63: 12.408228 | J63: 7.9132565
A64: 1996 | B64: -4 | C64: 10.978035 | D64: 11.490674 | E64: 11.79267 | F64: 9.0935826 | G64: 11.993138 | H64: 8.8711281 | I64: 14.851921 | J64: 10.017588
A65: 1997 | C65: 14.347172 | D65: 14.761562 | E65: 15.667562 | F65: 11.846959 | G65: 16.009606 | H65: 11.353757 | I65: 18.543577 | J65: 13.121043
A66: 1998 | C66: 17.829975 | D66: 17.843232 | E66: 19.092595 | F66: 15.308772 | G66: 20.836977 | H66: 12.463653 | I66: 23.689553 | J66: 16.119743
A67: 1999 | C67: 29.728147 | D67: 29.82579 | E67: 31.817561 | F67: 25.595463 | G67: 30.931687 | H67: 25.98321 | I67: 36.147377 | J67: 29.030915
A68: 2000 | C68: 58.239615 | D68: 58.738823 | E68: 61.727201 | F68: 53.353563 | G68: 64.857747 | H68: 41.770569 | I68: 78.787753 | J68: 55.797032
A69: 2001 | C69: 80.179897 | D69: 80.193895 | E69: 84.802958 | F69: 77.864641 | G69: 87.207883 | H69: 57.539159 | I69: 104.5946 | J69: 80.876942
A70: 2002 | C70: 90.234696 | D70: 90.081593 | E70: 92.502752 | F70: 92.429768 | G70: 95.334973 | H70: 76.159311 | I70: 109.28732 | J70: 88.415684
A71: 2003 | C71: 97.425504 | D71: 97.159466 | E71: 98.517397 | F71: 97.746284 | G71: 98.97268 | H71: 91.39002 | I71: 105.52796 | J71: 97.499012
A72: 2004 | C72: 100 | D72: 99.86 | E72: 99.91 | F72: 99.66 | G72: 100.13073 | H72: 99.562496 | I72: 100.14418 | J72: 100.03546
A73: 2005 | B73: -5 | C73: 102.08 | D73: 102.12 | E73: 101.06 | F73: 102.42 | G73: 102.4344 | H73: 101.62137 | I73: 99.610989 | J73: 102.50741
A74: 2006 | C74: 105.45 | D74: 105.54 | E74: 103.49 | F74: 105.23 | G74: 107.25042 | H74: 105.52643 | I74: 100.2456 | J74: 105.14711
A75: 2007 | C75: 107.84752 | D75: 107.82116 | E75: 105.25518 | F75: 107.66899 | G75: 110.41749 | H75: 108.32811 | I75: 101.07987 | J75: 107.14256
A76: 2008 | C76: 116.90683 | D76: 116.42765 | E76: 113.16581 | F76: 116.11844 | G76: 127.42953 | H76: 116.56523 | I76: 107.50349 | J76: 111.04006
A77: 2009 | C77: 122.93918 | D77: 122.19921 | E77: 117.92823 | F77: 122.17385 | G77: 135.56196 | H77: 121.85838 | I77: 114.03509 | J77: 115.65667
A78: 2010 | C78: 127.3089 | D78: 126.54271 | E78: 121.57083 | F78: 125.61173 | G78: 142.29999 | H78: 124.86711 | I78: 119.02618 | J78: 118.61905
A79: 2011 | C79: 133.00538 | D79: 131.28671 | E79: 127.34721 | F79: 131.16637 | G79: 151.28988 | H79: 128.75362 | I79: 126.70894 | J79: 122.09009
A80: 2012 | C80: 139.79095 | D80: 138.51853 | E80: 132.81358 | F80: 136.75628 | G80: 161.11033 | H80: 132.74902 | I80: 132.30094 | J80: 127.89187
A81: 2013 | C81: 143.59574 | D81: 142.47186 | E81: 136.15892 | F81: 141.29831 | G81: 165.7715 | H81: 135.84089 | I81: 135.11549 | J81: 131.52851
A82: 2014 | C82: 148.74971 | D82: 147.91776 | E82: 141.21232 | F82: 146.55198 | G82: 173.59417 | H82: 140.2187 | I82: 138.00247 | J82: 135.43324
A87: regresar al índice

Sheet 4.7.a
A1: 4.7.a ÍNDICE PONDERADO DE PRECIOS AL CONSUMIDOR POR CIUDADES Y POR CATEGORÍAS DE BIENES Y SERVICIOS (2015-2016) (1)
A2: (Familias de ingresos bajos, medios y altos de Quito, Guayaquil y Cuenca) (2)
A3: Base: enero - diciembre de 2014 = 100
A5: Año | C5: Indice Nacional | D5: Por ciudades | G5: Por grupo de bienes y servicios
D6: Quito | E6: Guayaquil | F6: Cuenca | G6: Alimentos | H6: Vivienda | I6: Indumentaria | J6: Diversos
A8: 2015 | C8: 103.22038 | D8: 102.83804 | E8: 103.38543 | F8: 103.23524 | G8: 104.31401 | H8: 107.20527 | I8: 98.61046 | J8: 102.55659
A9: 2016 | C9: 105.0043 | D9: 104.85543 | E9: 105.15814 | F9: 105.47547 | G9: 107.27835 | H9: 110.57192 | I9: 98.149169 | J9: 104.58089
A14: regresar al índice

Sheet 4.8
A1: 4.8 ÍNDICE PONDERADO DE PRECIOS AL CONSUMIDOR POR DIVISIONES DE BIENES Y SERVICIOS (1997-2004) (1)
A2: De las familias de ingresos bajos y medios
A3: Base: septiembre 1994 - agosto 1995 = 100
A5: Año | B5: ÍNDICE GENERAL | C5: Alimentos, bebidas y tabaco | D5: Vestido y calzado | E5: Alquiler, agua, electricidad, gas y otros combustibles | F5: Muebles, equipamiento y mantenimiento de la vivienda | G5: Salud | H5: Transporte | I5: Esparcimiento y cultura | J5: Educación | K5: Hoteles, cafeterías y restaurantes | L5: Bienes y servicios misceláneos
A7: 1997 | B7: 177.11 | C7: 181.2 | D7: 167.11 | E7: 197.1 | F7: 160.48 | G7: 169.97 | H7: 180.38 | I7: 147.8 | J7: 186.09 | K7: 178.88 | L7: 159.59
A8: 1998 | B8: 241.04 | C8: 253.01 | D8: 204.95583 | E8: 303.905 | F8: 206.17917 | G8: 225.29833 | H8: 255.26833 | I8: 192.20083 | J8: 237.7275 | K8: 242.53417 | L8: 196.495
A9: 1999 | B9: 366.96 | C9: 351.78 | D9: 323.4025 | E9: 481.05 | F9: 348.77167 | G9: 363.70083 | H9: 438.75417 | I9: 361.74167 | J9: 325.04917 | K9: 343.51083 | L9: 338.725
A10: 2000 | B10: 719.61 | C10: 776.77 | D10: 709.17083 | E10: 632.27417 | F10: 748.4225 | G10: 774.29417 | H10: 816.65667 | I10: 775.985 | J10: 520.34833 | K10: 626.4525 | L10: 752.55583
A11: 2001 | B11: 990.73 | C11: 1023.04 | D11: 926.26667 | E11: 956.58417 | F11: 971.67417 | G11: 1061.6858 | H11: 1211.73 | I11: 952.75917 | J11: 886.92667 | K11: 907.7375 | L11: 987.1075
A12: 2002 | B12: 1114.42 | C12: 1106.87 | D12: 939.48333 | E12: 1403.9417 | F12: 1027.8892 | G12: 1195.035 | H12: 1233.2667 | I12: 964.39583 | J12: 1237.2675 | K12: 1029.4408 | L12: 1009.2567
A13: 2003 | B13: 1202.78 | C13: 1133.78 | D13: 883.90583 | E13: 1806.3392 | F13: 1013.0475 | G13: 1257.5717 | H13: 1426.35 | I13: 942.22917 | J13: 1534.3642 | K13: 1113.8567 | L13: 951.625
A14: 2004 | B14: 1235.7616 | C14: 1147.3967 | D14: 821.95322 | E14: 2021.6127 | F14: 998.20914 | G14: 1281.0703 | H14: 1436.6306 | I14: 881.18601 | J14: 1787.736 | K14: 1126.9917 | L14: 869.16498
A19: regresar al índice

Sheet 4.8.a
A1: 4.8.a ÍNDICE PONDERADO DE PRECIOS AL CONSUMIDOR POR DIVISIONES DE BIENES Y SERVICIOS (2005 - 2014)
A2: De las familias de ingresos bajos, medios y altos
A3: Base: enero - diciembre 2004 = 100
A5: Año | B5: ÍNDICE GENERAL | C5: Alimentos y Bebidas No Alcohólicas (1) | D5: Bebidas Alcohólicas, Tabaco y estupefacientes (1) | E5: Prendas de Vestir y calzado | F5: Alojamiento, agua, gas, electricidad y otros | G5: Muebles, artículos para el hogar y conservación ordinaria | H5: Salud | I5: Transporte | J5: Comunicaciones (2) | K5: Recreación y Cultura | L5: Educación | M5: Restaurantes y Hoteles | N5: Bienes y Servicios Diversos (2)
A7: 2005 | B7: 102.07999 | C7: 102.89788 | D7: 106.14221 | E7: 99.610989 | F7: 102.87035 | G7: 99.534134 | H7: 101.32959 | I7: 102.2389 | J7: 98.452844 | K7: 102.52963 | L7: 109.35368 | M7: 100.97228 | N7: 98.133942
A8: 2006 | B8: 105.44713 | C8: 108.74206 | D8: 110.02359 | E8: 100.24561 | F8: 107.81476 | G8: 101.70223 | H8: 102.89166 | I8: 105.01333 | J8: 97.729633 | K8: 101.71577 | L8: 118.98487 | M8: 102.45316 | N8: 98.670906
A9: 2007 | B9: 107.84753 | C9: 112.28075 | D9: 115.57655 | E9: 101.07987 | F9: 110.31948 | G9: 105.00023 | H9: 105.2924 | I9: 107.85789 | J9: 97.181676 | K9: 99.778047 | L9: 125.27693 | M9: 104.05184 | N9: 98.730276
A10: 2008 | B10: 116.90683 | C10: 131.18691 | D10: 137.97387 | E10: 107.50349 | F10: 115.30278 | G10: 118.67497 | H10: 108.61897 | I10: 110.85217 | J10: 95.614296 | K10: 101.25149 | L10: 131.2337 | M10: 114.02753 | N10: 108.01155
A11: 2009 | B11: 122.93918 | C11: 138.90809 | D11: 155.80713 | E11: 114.03509 | F11: 117.79963 | G11: 128.64116 | H11: 112.19002 | I11: 113.22832 | J11: 95.940309 | K11: 103.30237 | L11: 136.34023 | M11: 122.66712 | N11: 124.74612
A12: 2010 | B12: 127.3089 | C12: 145.61615 | D12: 165.4898 | E12: 119.02618 | F12: 120.77793 | G12: 131.70072 | H12: 116.36557 | I12: 114.90436 | J12: 96.111224 | K12: 105.40435 | L12: 141.1002 | M12: 129.60174 | N12: 129.5941
A13: 2011 | B13: 133.00538 | C13: 155.40971 | D13: 172.40961 | E13: 126.70894 | F13: 123.38695 | G13: 137.72211 | H13: 120.04391 | I13: 117.57101 | J13: 98.082725 | K13: 105.60302 | L13: 147.83742 | M13: 135.98398 | N13: 134.92425
A14: 2012 | B14: 139.79095 | C14: 164.44104 | D14: 211.29222 | E14: 132.30094 | F14: 126.54439 | G14: 143.11787 | H14: 125.42093 | I14: 123.55702 | J14: 97.525656 | K14: 109.52802 | L14: 157.14707 | M14: 146.60413 | N14: 140.99481
A15: 2013 | B15: 143.59574 | C15: 167.37241 | D15: 235.42971 | E15: 135.11549 | F15: 129.3192 | G15: 146.73959 | H15: 130.93791 | I15: 124.73274 | J15: 97.553326 | K15: 110.4467 | L15: 166.794 | M15: 155.98096 | N15: 145.86827
A16: 2014 | B16: 148.74971 | C16: 174.93937 | D16: 250.1307 | E16: 138.00247 | F16: 134.11305 | G16: 150.42215 | H16: 135.55146 | I16: 125.34715 | J16: 97.180811 | K16: 112.76733 | L16: 176.54408 | M16: 164.49258 | N16: 154.00957
A21: regresar al índice

Sheet 4.8.b
A1: 4.8.b ÍNDICE PONDERADO DE PRECIOS AL CONSUMIDOR POR DIVISIONES DE BIENES Y SERVICIOS (2015 - 2016)
A2: De las familias de ingresos bajos, medios y altos
A3: Base: enero - diciembre 2014 = 100
A5: Año | B5: ÍNDICE GENERAL | C5: Alimentos y Bebidas No Alcohólicas (1) | D5: Bebidas Alcohólicas, Tabaco y estupefacientes (1) | E5: Prendas de Vestir y calzado | F5: Alojamiento, agua, gas, electricidad y otros | G5: Muebles, artículos para el hogar y conservación ordinaria | H5: Salud | I5: Transporte | J5: Comunicaciones (2) | K5: Recreación y Cultura | L5: Educación | M5: Restaurantes y Hoteles | N5: Bienes y Servicios Diversos (2)
A7: 2015 | B7: 103.22038 | C7: 104.13818 | D7: 108.75299 | E7: 97.329532 | F7: 107.28025 | G7: 104.13149 | H7: 102.81952 | I7: 104.63374 | J7: 95.082696 | K7: 99.29541 | L7: 102.16304 | M7: 105.6297 | N7: 104.18779
A8: 2016 | B8: 105.0043 | C8: 106.77876 | D8: 124.87976 | E8: 94.235301 | F8: 110.99719 | G8: 104.60875 | H8: 105.7043 | I8: 105.51381 | J8: 94.437888 | K8: 99.207773 | L8: 104.53354 | M8: 108.72719 | N8: 107.38748
A13: regresar al índice

Sheet 4.9
A1: 4.9 VARIACIÓN ANUAL DEL ÍNDICE PONDERADO DE PRECIOS AL CONSUMIDOR POR CIUDADES Y POR CATEGORÍAS DE BIENES
A2: Y SERVICIOS (1940-2014) (1)
A3: (Familias de ingresos bajos, medios y altos de Quito, Guayaquil y Cuenca) (2)
A4: Base: enero - diciembre de 2004 = 100
A6: Año | C6: Nacional | D6: Por ciudades | G6: Por grupo de bienes y servicios
D7: Quito | E7: Guayaquil | F7: Cuenca | G7: Alimentos | H7: Vivienda | I7: Indumentaria | J7: Diversos
A9: 1940 | C9: 3.55 | D9: 3.55
A10: 1941 | C10: 3.4246575 | D10: 3.4246575
A11: 1942 | C11: 28.476821 | D11: 28.476821
A12: 1943 | C12: 22.164948 | D12: 22.164948
A13: 1944 | C13: 22.78481 | D13: 22.78481
A14: 1945 | C14: 29.896907 | D14: 29.896907
A15: 1946 | C15: 14.814815 | D15: 14.814815
A16: 1947 | C16: 14.285714 | D16: 14.285714
A17: 1948 | C17: 11.895161 | D17: 11.895161
A18: 1949 | C18: -1.8018018 | D18: -1.8018018
A19: 1950 | C19: -0.55045872 | D19: -1.4678899
A20: 1951 | C20: 11.808118 | D20: 12.849162
A21: 1952 | C21: 3.30033 | D21: 3.30033
A22: 1953 | C22: 0.47923323 | D22: 0.47923323 | G22: -0.68493151 | H22: 2.7900147 | I22: 1.1006289 | J22: 1.3043478
A23: 1954 | C23: 3.6565978 | D23: 3.6565978 | G23: 6.3793103 | H23: -1.1428571 | I23: 2.0217729 | J23: 0
A24: 1955 | C24: 4.601227 | D24: 1.3803681 | G24: 11.669368 | H24: -7.3699422 | I24: 11.280488 | J24: 3.5765379
A25: 1956 | C25: -2.9325513 | D25: -4.6898638 | G25: -4.7895501 | H25: 1.8720749 | I25: -6.5753425 | J25: -4.8342541
A26: 1957 | C26: 1.0574018 | D26: 0.63492063 | G26: 1.6768293 | H26: 1.0719755 | I26: -0.8797654 | J26: -2.7576197
A27: 1958 | C27: 1.0463378 | D27: 1.7350158 | E27: 0.7204611 | G27: 0.44977511 | H27: 0.75757576 | I27: 0 | J27: 6.119403
A28: 1959 | C28: -0.29585799 | D28: 0.15503876 | E28: -0.57224607 | G28: -2.5373134 | H28: 3.4586466 | I28: 2.8106509 | J28: 0.70323488
A29: 1960 | C29: 0.59347181 | D29: 1.3931889 | E29: -0.14388489 | G29: -1.0719755 | H29: 3.9244186 | I29: -0.14388489 | J29: 1.5363128
A30: 1961 | C30: 5.0147493 | D30: 4.2748092 | E30: 5.6195965 | G30: 6.501548 | H30: 3.7762238 | I30: 8.2132565 | J30: 2.4759285
A31: 1962 | C31: 1.6853933 | D31: 2.7818448 | E31: 0.95497954 | G31: 0.14534884 | H31: 4.7169811 | I31: 4.9267643 | J31: 2.8187919
A32: 1963 | C32: 3.038674 | D32: 5.982906 | E32: 0.94594595 | G32: 3.628447 | H32: 1.9305019 | I32: 1.5228426 | J32: 9.2689295
A33: 1964 | C33: 1.3404826 | D33: 3.3602151 | E33: 3.480589 | G33: 3.3613445 | H33: 3.9141414 | I33: -4.25 | J33: -5.734767
A34: 1965 | C34: 6.3492063 | D34: 3.2509753 | E34: 5.0452781 | G34: 4.7425474 | H34: 4.2527339 | I34: 6.1357702 | J34: 3.8022814
A35: 1966 | C35: 3.7313433 | D35: 4.0302267 | E35: 3.3251232 | G35: 4.915912 | H35: 2.7972028 | I35: 4.1820418 | J35: 4.3956044
A36: 1967 | C36: 4.7961631 | D36: 3.874092 | E36: 5.601907 | G36: 6.4118372 | H36: 2.0408163 | I36: -0.47225502 | J36: 6.1988304
A37: 1968 | C37: 2.9748284 | D37: 4.1958042 | E37: 2.0316027 | G37: 3.8238702 | H37: 1.8888889 | I37: 1.3048636 | J37: 1.8722467
A38: 1969 | C38: 5.2222222 | D38: 6.4876957 | E38: 4.7566372 | G38: 7.8125 | H38: 1.7448201 | I38: 6.323185 | J38: 1.7297297
... A40: 1971 | C40: 9.5 | D40: 8.4 | E40: 9.8 | G40: 7.8 | H40: 11 | I40: 13 | J40: 9.8
A41: 1972 | C41: 7.6712329 | D41: 7.9335793 | E41: 7.4681239 | F41: 7.4204947 | G41: 10.204082 | H41: 6.036036 | I41: 6.7256637 | J41: 3.2786885
A42: 1973 | C42: 11.959288 | D42: 12.905983 | E42: 11.610169 | F42: 10.115132 | G42: 17.255892 | H42: 5.6924384 | I42: 10.613599 | J42: 7.0546737
A43: 1974 | C43: 22.727273 | D43: 23.39137 | E43: 22.171602 | F43: 23.226288 | G43: 31.155779 | H43: 11.977492 | I43: 21.064468 | J43: 12.191104
A44: 1975 | C44: 15.37037 | D44: 15.337423 | E44: 13.486638 | F44: 15.575758 | G44: 17.73399 | H44: 15.649677 | I44: 15.913313 | J44: 6.681351
A45: 1976 | C45: 10.540396 | D45: 10.691489 | E45: 9.7480832 | F45: 10.015732 | G45: 9.902371 | H45: 12.22843 | I45: 11.538462 | J45: 9.8417068
A46: 1977 | C46: 12.923524 | D46: 13.022585 | E46: 13.223553 | F46: 10.581506 | G46: 14.551607 | H46: 13.274336 | I46: 13.074713 | J46: 9.0225564
A47: 1978 | C47: 13.587655 | D47: 12.07483 | E47: 13.838695 | F47: 14.87069 | G47: 12.629247 | H47: 14.892578 | I47: 11.012283 | J47: 16.494253
A48: 1979 | C48: 10.113208 | D48: 9.8634294 | E48: 9.9496709 | F48: 11.594747 | G48: 9.6393443 | H48: 9.8597535 | I48: 8.4318962 | J48: 13.46818
A49: 1980 | C49: 12.611378 | D49: 13.017956 | E49: 12.253521 | F49: 15.131137 | G49: 9.8086124 | H49: 16.363636 | I49: 18.121042 | J49: 13.913043
A50: 1981 | B50: -3 | C50: 14.729154 | D50: 16.406966 | E50: 13.111669 | F50: 18.457944 | G50: 13.208061 | H50: 15.558511 | I50: 15.90706 | J50: 17.709924
A51: 1982 | C51: 16.335541 | D51: 12.633833 | E51: 14.877868 | F51: 23.308271 | G51: 17.136659 | H51: 15.209125 | I51: 15.866084 | J51: 16.666667
A52: 1983 | C52: 48.387097 | D52: 45.183777 | E52: 50.322165 | F52: 48.669623 | G52: 77.901235 | H52: 20.132013 | I52: 30.213568 | J52: 35.431089
A53: 1984 | C53: 31.202046 | D53: 29.201222 | E53: 30.604372 | F53: 34.936614 | G53: 36.988203 | H53: 22.747253 | I53: 28.895321 | J53: 26.858736
A54: 1985 | C54: 28.005198 | D54: 28.783784 | E54: 27.404004 | F54: 28.212213 | G54: 30.699088 | H54: 15.085049 | I54: 26.459581 | J54: 33.040293
A55: 1986 | C55: 23.020305 | D55: 22.455404 | E55: 23.338485 | F55: 23.987069 | G55: 23.197674 | H55: 17.269545 | I55: 28.973069 | J55: 24.72467
A56: 1987 | C56: 29.502785 | D56: 28.170523 | E56: 32.26817 | F56: 28.22875 | G56: 28.739972 | H56: 25.552239 | I56: 26.824231 | J56: 34.635762
A57: 1988 | C57: 58.228453 | D57: 55.941835 | E57: 59.766303 | F57: 53.693914 | G57: 64.332845 | H57: 38.822846 | I57: 54.966528 | J57: 58.583374
A58: 1989 | C58: 75.634313 | D58: 72.979636 | E58: 76.092113 | F58: 80.349268 | G58: 87.96193 | H58: 48.867745 | I58: 66.876824 | J58: 66.211745
A59: 1990 | C59: 48.520981 | D59: 44.77353 | E59: 50.339563 | F59: 46.55223 | G59: 47.521658 | H59: 46.567813 | I59: 47.092983 | J59: 52.500622
A60: 1991 | C60: 48.722402 | D60: 45.92767 | E60: 49.854402 | F60: 48.226382 | G60: 48.608281 | H60: 45.002616 | I60: 50.913242 | J60: 49.351444
A61: 1992 | C61: 54.605815 | D61: 56.892304 | E61: 53.943697 | F61: 50.496409 | G61: 54.030206 | H61: 47.137014 | I61: 47.462809 | J61: 61.264509
A62: 1993 | C62: 44.955054 | D62: 48.386735 | E62: 43.032382 | F62: 45.815195 | G62: 41.832431 | H62: 45.930589 | I62: 38.745805 | J62: 54.238149
... A64: 1995 | C64: 22.933831 | D64: 24.645245 | E64: 22.466878 | F64: 22.590606 | G64: 21.030175 | H64: 25.044616 | I64: 19.016093 | J64: 26.568288
A65: 1996 | B65: -4 | C65: 24.389101 | D65: 26.424355 | E65: 23.650806 | F65: 28.315965 | G65: 23.735914 | H65: 24.662194 | I65: 19.694132 | J65: 26.592482
A66: 1997 | C66: 30.689795 | D66: 28.465592 | E66: 32.858484 | F66: 30.278239 | G66: 33.489712 | H66: 27.985492 | I66: 24.85642 | J66: 30.980063
A67: 1998 | C67: 24.275191 | D67: 20.876308 | E67: 21.860658 | F67: 29.22111 | G67: 30.152968 | H67: 9.7755816 | I67: 27.750723 | J67: 22.854132
A68: 1999 | C68: 66.731282 | D68: 67.154642 | E68: 66.648702 | F68: 67.194748 | G68: 48.446135 | H68: 108.47187 | I68: 52.587839 | J68: 80.095393
A69: 2000 | C69: 95.907318 | D69: 96.939708 | E69: 94.00356 | F69: 108.4493 | G69: 109.6806 | H69: 60.759849 | I69: 117.96257 | J69: 92.198669
A70: 2001 | C70: 37.672438 | D70: 36.52622 | E70: 37.383449 | F70: 45.940845 | G70: 34.460242 | H70: 37.75048 | I70: 32.754899 | J70: 44.948465
A71: 2002 | C71: 12.540298 | D71: 12.329738 | E71: 9.0796291 | F71: 18.705701 | G71: 9.3192145 | H71: 32.360834 | I71: 4.4865734 | J71: 9.3212496
A72: 2003 | C72: 7.9690059 | D72: 7.8571801 | E72: 6.5021248 | F72: 5.751953 | G72: 3.815711 | H72: 19.998485 | I72: -3.4398778 | J72: 10.273435
A73: 2004 | C73: 2.6425278 | D73: 2.7794862 | E73: 1.4135608 | F73: 1.9578397 | G73: 1.1693326 | H73: 8.9396852 | I73: -5.1057224 | J73: 2.6061681
A74: 2005 | B74: -5 | C74: 2.08 | D74: 2.2631684 | E74: 1.1510359 | F74: 2.769416 | G74: 2.2970139 | H74: 2.0691041 | I74: -0.52925904 | J74: 2.4690124
A75: 2006 | C75: 3.3013323 | D75: 3.3490012 | E75: 2.4045122 | F75: 2.7436048 | G75: 4.7015608 | H75: 3.8427511 | I75: 0.63708542 | J75: 2.5751225
A76: 2007 | C76: 2.2736037 | D76: 2.1614153 | E76: 1.7056538 | F76: 2.3177706 | G76: 2.9529691 | H76: 2.654957 | I76: 0.83223192 | J76: 1.8977751
A77: 2008 | C77: 8.4001117 | D77: 7.9821913 | E77: 7.5156657 | F77: 7.8476146 | G77: 15.407014 | H77: 7.603866 | I77: 6.354994 | J77: 3.6376771
A78: 2009 | C78: 5.1599683 | D78: 4.9572057 | E78: 4.2083569 | F78: 5.2148614 | G78: 6.3819034 | H78: 4.5409364 | I78: 6.0757103 | J78: 4.1576081
A79: 2010 | C79: 3.5543773 | D79: 3.5544474 | E79: 3.0888318 | F79: 2.8139217 | G79: 4.9704495 | H79: 2.4690316 | I79: 4.3768012 | J79: 2.5613583
A80: 2011 | C80: 4.4745327 | D80: 3.7489309 | E80: 4.7514496 | F80: 4.4220728 | G80: 6.3175581 | H80: 3.1125191 | I80: 6.4546794 | J80: 2.9262058
A81: 2012 | C81: 5.1017218 | D81: 5.5084162 | E81: 4.2924938 | F81: 4.2616908 | G81: 6.491147 | H81: 3.1031355 | I81: 4.4132623 | J81: 4.7520456
A82: 2013 | C82: 2.7217758 | D82: 2.8540061 | E82: 2.5188186 | F82: 3.3212616 | G82: 2.8931549 | H82: 2.3291104 | I82: 2.1273838 | J82: 2.8435287
A83: 2014 | C83: 3.5892202 | D83: 3.8224435 | E83: 3.7114026 | F83: 3.7181437 | G83: 4.718946 | H83: 3.2227507 | I83: 2.1366807 | J83: 2.9687308
A88: regresar al índice

Sheet 4.9.a
A1: 4.9.a VARIACIÓN ANUAL DEL ÍNDICE PONDERADO DE PRECIOS AL CONSUMIDOR POR CIUDADES Y POR CATEGORÍAS DE BIENES
A2: Y SERVICIOS (2015-2016) (1)
A3: (Familias de ingresos bajos, medios y altos de Quito, Guayaquil y Cuenca) (2)
A4: Base: enero - diciembre de 2014 = 100
A6: Año | C6: Nacional | D6: Por ciudades | G6: Por grupo de bienes y servicios
D7: Quito | E7: Guayaquil | F7: Cuenca | G7: Alimentos | H7: Vivienda | I7: Indumentaria | J7: Diversos
A9: 2015 | C9: 3.9666462 | D9: - | E9: - | F9: - | G9: - | H9: - | I9: - | J9: -
A10: 2016 | C10: 1.7282646 | D10: 1.9617116 | E10: 1.7146613 | F10: 2.1700241 | G10: 2.8417488 | H10: 3.1403817 | I10: -0.46779093 | J10: 1.9738383
A15: regresar al índice

Sheet 4.10
A1: 4.10 VARIACIÓN ANUAL DEL ÍNDICE PONDERADO DE PRECIOS AL CONSUMIDOR POR DIVISIONES DE BIENES Y SERVICIOS (1997-2004) (1)
A2: Familias de ingresos bajos y medios
A3: Base: septiembre, 1994 - agosto, 1995 = 100
A5: Año | B5: GENERAL | C5: Alimentos Bebidas y Tabaco | D5: Vestido y Calzado | E5: Alquiler, Agua, Gas, Electricidad y otros | F5: Muebles, Equipamiento, Mantenimiento de Vivienda | G5: Salud | H5: Transporte | I5: Esparcimiento y Cultura | J5: Educación | K5: Hoteles, Cafeterías y Restaurantes | L5: Bienes y Servicios Misceláneos | M5: Valores de las UVC (1)
A7: 1997 | B7: 30.6 | C7: - | D7: - | E7: - | F7: - | G7: - | H7: - | I7: - | J7: - | K7: - | L7: -
A8: 1998 | B8: 36.096211 | C8: 39.630243 | D8: 22.647258 | E8: 54.188229 | F8: 28.47655 | G8: 32.551823 | H8: 41.516983 | I8: 30.041159 | J8: 27.74867 | K8: 35.584843 | L8: 23.124883
A9: 1999 | B9: 52.240292 | C9: 39.037983 | D9: 57.791313 | E9: 58.289597 | F9: 69.159509 | G9: 61.43077 | H9: 71.879591 | I9: 88.210249 | J9: 36.731832 | K9: 41.633997 | L9: 72.383521
A10: 2000 | B10: 96.100392 | C10: 120.8113 | D10: 119.28428 | E10: 31.436268 | F10: 114.5881 | G10: 112.89315 | H10: 86.130806 | I10: 114.51358 | J10: 60.082962 | K10: 82.367611 | L10: 122.1731
A11: 2001 | B11: 37.675963 | C11: 31.704366 | D11: 30.612629 | E11: 51.292622 | F11: 29.829631 | G11: 37.1166 | H11: 48.376919 | I11: 22.780616 | J11: 70.448642 | K11: 44.901249 | L11: 31.167344
A12: 2002 | B12: 12.484733 | C12: 8.1942055 | D12: 1.4268749 | E12: 46.766141 | F12: 5.7853756 | G12: 12.560134 | H12: 1.7773486 | I12: 1.221365 | J12: 39.500541 | K12: 13.407327 | L12: 2.2438454
A13: 2003 | B13: 7.9287881 | C13: 2.4311798 | D13: -5.9157516 | E13: 28.661981 | F13: -1.4438976 | G13: 5.2330406 | H13: 15.656252 | I13: -2.2985029 | J13: 24.012323 | K13: 8.2001637 | L13: -5.7103082
A14: 2004 | B14: 2.7421162 | C14: 1.2010013 | D14: -7.0089606 | E14: 11.917668 | F14: -1.4647245 | G14: 1.8685689 | H14: 0.72076008 | I14: -6.4785892 | J14: 16.51315 | K14: 1.1792385 | L14: -8.6651803
A19: regresar al índice

Sheet 4.10.a
A1: 4.10.a VARIACIÓN ANUAL DEL ÍNDICE PONDERADO DE PRECIOS AL CONSUMIDOR POR DIVISIONES DE BIENES Y SERVICIOS (2005-2014)
A2: De las familias de ingresos altos, medios y bajos
A3: Base: enero - diciembre 2004 = 100
A5: Año | B5: GENERAL | C5: Alimentos y Bebidas No Alcohólicas (1) | D5: Bebidas Alcohólicas, Tabaco y estupefacientes (1) | E5: Prendas de Vestir y calzado | F5: Alojamiento, agua, gas, electricidad y otros | G5: Muebles y artículos para el hogar y conservación ordinaria | H5: Salud | I5: Transporte | J5: Comunicaciones (2) | K5: Recreación y Cultura | L5: Educación | M5: Restaurantes y Hoteles | N5: Bines y Servicios Diversos (2)
A7: 2005 | B7: 2.1230811 | C7: 2.7320285 | D7: 6.59156 | E7: -0.25049528 | F7: 3.3723294 | G7: -0.1087591 | H7: 0.96589085 | I7: 2.2797225 | J7: -1.8119741 | K7: 2.6567139 | L7: 9.8560489 | M7: 0.80449923 | N7: -2.1183105
A8: 2006 | B8: 3.2985304 | C8: 5.6795898 | D8: 3.6567762 | E8: 0.63709878 | F8: 4.8064471 | G8: 2.1782394 | H8: 1.5415714 | I8: 2.7136734 | J8: -0.73457578 | K8: -0.79378763 | L8: 8.8073694 | M8: 1.4666139 | N8: 0.54717395
A9: 2007 | B9: 2.2764006 | C9: 3.2542088 | D9: 5.0470677 | E9: 0.83221853 | F9: 2.3231697 | G9: 3.2428004 | H9: 2.3332688 | I9: 2.7087614 | J9: -0.56068657 | K9: -1.9050321 | L9: 5.2881225 | M9: 1.5604094 | N9: 0.060169415
A10: 2008 | B10: 8.4000959 | C10: 16.838291 | D10: 19.378768 | E10: 6.354994 | F10: 4.5171537 | G10: 13.023537 | H10: 3.1593689 | I10: 2.7761371 | J10: -1.6128349 | K10: 1.4767206 | L10: 4.7548779 | M10: 9.5872308 | N10: 9.400636
A11: 2009 | B11: 5.1599683 | C11: 5.8856364 | D11: 12.9251 | E11: 6.0757103 | F11: 2.1654702 | G11: 8.397889 | H11: 3.2876815 | I11: 2.1435323 | J11: 0.34096668 | K11: 2.0255339 | L11: 3.891173 | M11: 7.5767517 | N11: 15.493312
A12: 2010 | B12: 3.5543773 | C12: 4.8291339 | D12: 6.2145287 | E12: 4.3768012 | F12: 2.5282762 | G12: 2.3783693 | H12: 3.721854 | I12: 1.4802244 | J12: 0.17814692 | K12: 2.0347795 | L12: 3.4912479 | M12: 5.6532034 | N12: 3.8862829
A13: 2011 | B13: 4.4745327 | C13: 6.7256017 | D13: 4.1814064 | E13: 6.4546794 | F13: 2.1601804 | G13: 4.5720244 | H13: 3.1610212 | I13: 2.3207566 | J13: 2.0512706 | K13: 0.18848799 | L13: 4.7747705 | M13: 4.9245013 | N13: 4.1129537
A14: 2012 | B14: 5.1017218 | C14: 5.8113003 | D14: 22.552464 | E14: 4.4132623 | F14: 2.5589722 | G14: 3.9178577 | H14: 4.4792145 | I14: 5.0913974 | J14: -0.56795833 | K14: 3.7167429 | L14: 6.2972258 | M14: 7.8098542 | N14: 4.499237
A15: 2013 | B15: 2.7217758 | C15: 1.7826252 | D15: 11.423747 | E15: 2.1273838 | F15: 2.1927573 | G15: 2.5305891 | H15: 4.3987719 | I15: 0.95156755 | J15: 0.028372047 | K15: 0.8387637 | L15: 6.1387928 | M15: 6.3960192 | N15: 3.4564842
A16: 2014 | B16: 3.5892202 | C16: 4.521033 | D16: 6.2443227 | E16: 2.1366807 | F16: 3.7069878 | G16: 2.5095882 | H16: 3.5234629 | I16: 0.49258189 | J16: -0.38185777 | K16: 2.1011366 | L16: 5.8455774 | M16: 5.4568354 | N16: 5.5812676
A21: regresar al índice

Sheet 4.10.b
A1: 4.10.b VARIACIÓN ANUAL DEL ÍNDICE PONDERADO DE PRECIOS AL CONSUMIDOR POR DIVISIONES DE BIENES Y SERVICIOS (2015-2016)
A2: De las familias de ingresos altos, medios y bajos
A3: Base: enero - diciembre 2014 = 100
A5: Año | B5: GENERAL | C5: Alimentos y Bebidas No Alcohólicas (1) | D5: Bebidas Alcohólicas, Tabaco y estupefacientes (1) | E5: Prendas de Vestir y calzado | F5: Alojamiento, agua, gas, electricidad y otros | G5: Muebles y artículos para el hogar y conservación ordinaria | H5: Salud | I5: Transporte | J5: Comunicaciones (2) | K5: Recreación y Cultura | L5: Educación | M5: Restaurantes y Hoteles | N5: Bines y Servicios Diversos (2)
A7: 2015 | B7: 3.9666462 | C7: - | D7: - | E7: - | F7: - | G7: - | H7: - | I7: - | J7: - | K7: - | L7: - | M7: - | N7: -
A8: 2016 | B8: =+'4.8.b'!B8/'4.8.b'!B7*100-100 -> 1.7282646 | C8: =+'4.8.b'!C8/'4.8.b'!C7*100-100 -> 2.5356521 | D8: =+'4.8.b'!D8/'4.8.b'!D7*100-100 -> 14.828801 | E8: =+'4.8.b'!E8/'4.8.b'!E7*100-100 -> -3.1791286 | F8: =+'4.8.b'!F8/'4.8.b'!F7*100-100 -> 3.4647038 | G8: =+'4.8.b'!G8/'4.8.b'!G7*100-100 -> 0.45832614 | H8: =+'4.8.b'!H8/'4.8.b'!H7*100-100 -> 2.8056721 | I8: =+'4.8.b'!I8/'4.8.b'!I7*100-100 -> 0.84109416 | ... N8: =+'4.8.b'!N8/'4.8.b'!N7*100-100 -> 3.0710812
A13: regresar al índice

Sheet 4.11
A1: 4.11 SALARIO MÍNIMO VITAL (1936 - 1968) (1)
A3: Año | B3: Fecha de vigencia | C3: Clase de trabajador | D3: Región | E3: Incrementos
F4: -en sucres-
F5: mensual | G5: diario
A7: 1936 | B7: 4-II-1937 | C7: Obrero manual | D7: Sierra | G7: mínimo 1,00
D8: Costa | G8: mínimo 2,00
D9: Quito | G9: mínimo 1,50
C11: Trabajador agrícola | D11: Sierra | G11: mínimo 0,65
D12: Costa | G12: mínimo 1,20
A14: 1942 | B14: 14-II-1942 | C14: Empleados privados | E14: incremento
C15: y obreros | E15: del 25% | F15: hasta 100 | G15: hasta 3,0
E16: incremento
E17: del 20% | F17: 101 a 200 | G17: 3,05 a 6,00
E18: incremento
E19: del 15% | F19: 201 a 300 | G19: 6,05 a 10,00
E20: incremento
E21: del 10% | F21: 301 a 500 | G21: 10,05 a 16,00
C22: Trabajador agrícola | D22: Sierra | F22: no menos de
F23: 1,00 diario
A25: 1953 | B25: 1-VIII-1953 | C25: Empleados privados
C26: y obreros | D26: Costa | E26: incremento
E27: del 40% | F27: hasta 200 | G27: hasta 7,00
E28: incremento
E29: del 30% | F29: 201 a 300 | G29: 7,05 a 10,00
E30: incremento
E31: del 25% | F31: 301 a 400 | G31: 10,05 a 14,00
E32: incremento
E33: del 15% | F33: 401 a 500 | G33: 14,05 a 17,00
D34: Sierra | E34: incremento
E35: del 30% | F35: hasta 200 | G35: hasta 7,00
E36: incremento
E37: del 20% | F37: 201 a 300 | G37: 7,05 a 10,00
E38: incremento
E39: del 15% | F39: 301 a 400 | G39: 10,05 a 14,00
E40: incremento
E41: del 10% | F41: 401 a 500 | G41: 14,05 a 17,00
A43: 1960 | B43: 4-IX-1960 | C43: Trabajador agrícola: | D43: Sierra
C44: Jornaleros | G44: mínimo 6,00
C45: Huasipungueros | G45: mínimo 3,00
A47: 1965 | B47: 24-VII-1965 | C47: Trabajador agrícola: | D47: Sierra
C48: Jornaleros | G48: mínimo 6,00
C49: Huasipungueros | G49: mínimo 6,00
A51: 1968 | B51: 8-X-1968 | C51: Empleados privados | D51: Nacional | F51: mínimo 600
C52: y públicos
A57: regresar al índice

Sheet 4.12
A1: 4.12 SALARIO MÍNIMO VITAL GENERAL (S.M.V) Y SALARIO BÁSICO
A2: UNIFICADO (S.B.U.) (1968-2016) (1)
A4: Año | B4: Sucres | C4: Dólares
A7: 1968 oct. | B7: 600 | C7: 27
A8: 1969 | B8: 600 | C8: 27
A9: 1970 | B9: 600 | C9: 26
A10: 1971 | B10: 750 | C10: 29
A11: 1972 | B11: 750 | C11: 29
A12: 1973 | B12: 750 | C12: 30
A13: 1974 | B13: 1000 | C13: 40
A14: 1975 ene | B14: 1000 | C14: 40
A15: 1975 may | B15: 1250 | C15: 50
A16: 1976 | B16: 1500 | C16: 56
A17: 1977 | B17: 1500 | C17: 55
A18: 1978 | B18: 1500 | C18: 56
A19: 1979 | B19: 2000 | C19: 72
A20: 1980 | B20: 4000 | C20: 144
A21: 1981 | B21: 4000 | C21: 128
A22: 1982 ene | B22: 4000 | C22: 115
A23: 1982 nov | B23: 4600 | C23: 78
A24: 1983 ene | B24: 4600 | C24: 69
A25: 1983 jul | B25: 5600 | C25: 57
A26: 1984 | B26: 6600 | C26: 67
A27: 1985 ene | B27: 6600 | C27: 54
A28: 1985 mar | B28: 8500 | C28: 70
A29: 1986 ene | B29: 10000 | C29: 76
A30: 1986 ago | B30: 12000 | C30: 71
A31: 1987 ene | B31: 12000 | C31: 82
A32: 1987 jul | B32: 14500 | C32: 74
A33: 1988 ene | B33: 14500 | C33: 54
A34: 1988 jun | B34: 19000 | C34: 38
A35: 1988 sep | B35: 22000 | C35: 42
A36: 1989 ene | B36: 22000 | C36: 41
A37: 1989 may | B37: 27000 | C37: 50
A38: 1990 | B38: 32000 | C38: 39
A39: 1991 | B39: 40000 | C39: 36
A40: 1992 ene | B40: 40000 | C40: 30
A41: 1992 jun | B41: 60000 | C41: 40
A42: 1993 ene | B42: 60000 | C42: 32
A43: 1993 jul | B43: 66000 | C43: 34
A44: 1994 ene | B44: 66000 | C44: 32
A45: 1994 jul | B45: 70000 | C45: 32
A46: 1995 ene | B46: 75000 | C46: 32
A47: 1995 jul | B47: 85000 | C47: 33
A48: 1996 | B48: 95000 | C48: 30
A49: 1997 ene | B49: 95000 | C49: 23.757127
A50: 1997 jul | B50: 100000 | C50: 25.007502
A51: 1998 | B51: 100000 | C51: 18.360752
A52: 1999 | B52: 100000 | C52: 8.407035
A53: 2000 (2) | B53: 100000 | C53: 4
A54: 2000 (3) (4) | B54: - | C54: 56.7
B55: - | C55: 85.7
A56: 2001 (5) | B56: - | C56: 121.32708
A57: 2002 | B57: - | C57: 138.15312
A58: 2003 | B58: - | C58: 158.11007
A59: 2004 | B59: - | C59: 166.13972
A60: 2005 | B60: - | C60: 174.90021
A61: 2006 | B61: - | C61: 186.59722
A62: 2007 | B62: - | C62: 198.26389
A63: 2008 | B63: - | C63: 233.125
A64: 2009 | B64: - | C64: 254.20833
A65: 2010 | B65: - | C65: 279.84722
A66: 2011 | B66: - | C66: 307.83333
A67: 2012 | B67: - | C67: 340.47222
A68: 2013 | B68: - | C68: 370.81944
... A71: 2016 | B71: - | C71: 426.9166
A76: regresar al índice

Sheet 4.13
A1: 4.13 POBLACIÓN
A3: Año | B3: Población total (1)
A6: 1927 | B6: 2257357.5
A7: 1928 | B7: 2297561
A8: 1929 | B8: 2338480.6
A9: 1930 | B9: 2380128.9
A10: 1931 | B10: 2422519
A11: 1932 | B11: 2465664.1
A12: 1933 | B12: 2509577.6
A13: 1934 | B13: 2554273.1
A14: 1935 | B14: 2599764.7
A15: 1936 | B15: 2646066.6
A16: 1937 | B16: 2693193
A17: 1938 | B17: 2741158.8
... A79: 2000 | B79: 12298745
A80: 2001 (2) | B80: 12156608
A81: 2002 | B81: 12660727
A82: 2003 | B82: 12842576
A83: 2004 | B83: 13026890
A84: 2005 | B84: 13215089
A85: 2006 | B85: 13408270
A86: 2007 | B86: 13605486
A87: 2008 | B87: 13805092
A88: 2009 | B88: 14005449
A89: 2010 | B89: 14204900
A90: 2010 (3) | B90: 14483399
A91: 2010 (4) | B91: 15012228
A92: 2011 | B92: 15266431
A93: 2012 | B93: 15520973
A94: 2013 | B94: 15774749
A95: 2014 | B95: 16027466
A96: 2015 | B96: 16278844
A97: 2016 | B97: 16528730
A102: regresar al índice

Sheet 4.14
A1: 4.14 CANASTA DE BIENES Y SERVICIOS PARA EL CÁLCULO DEL ÍNDICE DE
A2: PRECIOS AL CONSUMIDOR - COMPONENTES Y PONDERADORES -
A3: Base: agosto 1950-julio1951
A5: ALIMENTOS | B5: 52
A7: Carnes y pescados | B7: 8.3
A8: Carne de res de 1ra. | B8: 6.7
A9: Carne de res de 2da. | B9: 0.4
A10: Carne de cordero | B10: 0.1
A11: Carne de cerdo | B11: 1.1
A12: Corvina | B12: X
A14: Cereales y harinas | B14: 13.6
A15: Arroz de castilla | B15: 3.7
A16: Arroz de cebada | B16: 0.3
A17: Avena en paquete | B17: 0.3
A18: Avena suelta | B18: 0.3
A19: Fideos | B19: 1.3
A20: Harina de cebada | B20: 0.6
A21: Harina de habas | B21: 0.2
A22: Harina de plátano | B22: 0.1
A23: Harina de trigo importada | B23: 0.2
A24: Harina de trigo nacional | B24: 0.1
A25: Maíz | B25: 0.6
... A107: Reparación corridas (mujer) | B107: 0.4
A108: Zapatos de niño | B108: X
A109: Zapatos para hombre | B109: 1.2
A110: Reparación corridas (hombre) | B110: 0.6
A112: Telas | B112: 4.7
A113: Lienzo "Vencedor" | B113: 0.2
A114: Peter Pan | B114: 0.1
A115: Gabardina algodón | B115: 0.1
A116: Bramante algodón | B116: 0.3
A117: Franela | B117: 0.7
A118: Seda opaca | B118: 0.5
A119: Terciopelo de lana | B119: 0.5
A120: Casimir nacional | B120: 0.3
A121: Casimir extranjero | B121: 2
... A132: ENSERES DOMESTICOS | B132: 3
A133: Sillas de eucalipto | B133: X
A134: Sillas de cedro | B134: 0.1
A135: Camas de hierro | B135: 0.9
A136: Camas de eucalipto | B136: 0.2
A137: Mesas de cedro | B137: 0.1
A138: Mesas de aliso | B138: X
A139: Cobijas | B139: 0.7
A140: Reverberos de gasolina | B140: 0.1
A141: Platos | B141: 0.2
A142: Cucharas | B142: 0.2
A143: Ollas | B143: 0.2
A144: Planchas eléctricas | B144: 0.1
A145: Escobas | B145: 0.2
A147: MISCELANEOS | B147: 12.4
A149: Otros gastos de casa | B149: 2.5
A150: Espermas | B150: 0.1
A151: Fósforos | B151: 0.2
A152: Jabón para lavar ropa | B152: 1.9
... A167: Corte de pelo | B167: 0.9
A168: Afeitada | B168: X
A169: Permanentes | B169: 0.1
A170: Jabón para tocador, extranjero | B170: 0.1
A171: Jabón para tocador, nacional | B171: 0.1
A172: Dentríficos | B172: 0.4
A173: Polvo facial | B173: 0.2
A175: Diversiones | B175: 5
A176: Cine, luneta | B176: 1.1
A177: Cine, galería | B177: X
A178: Cigarrillos | B178: 1.6
A179: Periódicos | B179: 1.1
A180: Tubos para radio | B180: 1.2
A182: Transportes | B182: 1.4
A183: Omnibus | B183: 1.4
A185: (X) PONDERACIONES MENORES QUE 0.1
A190: regresar al índice

Sheet 4.15
A1: 4.15 CANASTA DE BIENES Y SERVICIOS PARA EL CÁLCULO DEL ÍNDICE DE
A2: PRECIOS AL CONSUMIDOR - COMPONENTES Y PONDERADORES -
A3: Base: 1965
A5: ALIMENTOS Y BEBIDAS | B5: 41.8
A7: Cereales y derivados | B7: 10.2
A8: Pan de trigo | B8: 6.0792
A9: Fideo al detal | B9: 0.8364
A10: Arroz de castilla | B10: 2.9274
A11: Avena al detal | B11: 0.357
A13: Carnes y preparaciones de carnes | B13: 6.8
A14: Carne de res con hueso (costilla) | B14: 4.046
A15: Carne de res sin hueso | B15: 2.1556
A16: Carne de gallina | B16: 0.5984
A18: Pescados y mariscos | B18: 0.5
A19: Corvina de mar | B19: 0.222
... A68: Ajo | B68: 0.1344
A70: Café, té y otras bebidas no alcohólicas
A71: consumidas en el hogar | B71: 1.8
A72: Café molido | B72: 0.8766
A73: Café soluble (si café) | B73: 0.4824
A74: Chocolate en pasta | B74: 0.2034
A75: Bebidas gaseosas | B75: 0.2376
A77: Otros productos alimenticios | B77: 0.3
A78: Chocolates para comer | B78: 0.1539
A79: Sopas secas (maggi) | B79: 0.0789507
A80: Salsa de tomate | B80: 0.040501709
A82: Bebidas alcohólicas en el hogar | B82: 0.6
A83: Cerveza | B83: 0.0738
A84: Mallorca | B84: 0.0090774
A85: Aguardiente de caña | B85: 0.0011165202
A87: Alimentos y bebidas consumidos
A88: fuera del hogar | B88: 2.3
A89: Almuerzos y comidas en restaurantes y | B89: 2.3
A90: similares
A92: VIVIENDA | B92: 19.7
A94: Alquiler | B94: 9
A95: Alquiler | B95: 9
A97: Impuesto sobre bienes raíces | B97: 0.3
A98: Impuesto sobre bienes raíces | B98: 0.3
A100: Alumbrado y combustible | B100: 4.1
A101: Gas | B101: 0.1517
A102: Gasolina | B102: 1.9926
A103: Kerosene | B103: 0.1394
A104: Energía Eléctrica | B104: 1.5334
A105: Fósforos | B105: 0.369
A107: Lavado y mantenimiento | B107: 3.5
... A212: Periódicos "El Comercio" | B212: 0.486
A213: Juguetes y equipo de juego y deporte, pelota
A214: para fútbol No. 5 nacional | B214: 0.6084
A215: Radio "Nec" japonés 2 bandas, 8 transistores | B215: 0.486
A217: Cigarrillos y tabaco | B217: 0.8
A218: Cigarrilos Full Blanco nacional 18 unidades | B218: 0.8
A220: Educación | B220: 3
A221: Gastos de matrícula Enseñanza Primaria | B221: 0.73529412
A222: Pensión de enseñanza primaria | B222: 1.0911765
A223: Textos, libros y equipos de escuela: 3 libros | B223: 1.1735294
A225: Viajes | B225: 3.6
A226: Viajes urbanos bus ordinario | B226: 2.9988
A227: Viajes escolares mensuales | B227: 0.612
A229: Comunicaciones | B229: 0.5
... A236: Interés quirografario | B236: 0.70588235
A241: regresar al índice

Sheet 4.16
A1: 4.16 CANASTA DE BIENES Y SERVICIOS PARA EL CÁLCULO DEL ÍNDICE DE
A2: PRECIOS AL CONSUMIDOR - COMPONENTES Y PONDERADORES -
A3: Base: abril 1978-mayo 1979
A5: ALIMENTOS Y BEBIDAS | B5: 39.5976
A7: Cereales y derivados | B7: 6.7236
A8: Arroz | B8: 4.102
A9: Avena | B9: 0.0771
A10: Fideo | B10: 0.5667
A11: Harina de trigo | B11: 0.0685
A12: Maíz | B12: 0.0679
A13: Pan | B13: 1.8414
A15: Carnes y preparaciones | B15: 7.7533
A16: Carne de res con hueso | B16: 2.315
A17: Carne de res sin hueso | B17: 4.1049
A18: Costilla de cerdo | B18: 0.1195
... A289: Llanta y tubo | B289: 0.2403
A294: regresar al índice

Sheet 4.17
A1: 4.17 CANASTA DE BIENES Y SERVICIOS PARA EL CÁLCULO DEL ÍNDICE DE
A2: PRECIOS AL CONSUMIDOR - COMPONENTES Y PONDERADORES -
A3: Base: septiembre 1994-agosto 1995
A5: ALIMENTOS Y BEBIDAS | B5: 43.209
A7: Cereales y derivados | B7: 5.5085
A8: Arroz | B8: 2.6921
A9: Avena | B9: 0.1693
A10: Fideo | B10: 0.4443
A11: Pan | B11: 2.2028
A13: Carnes y preparaciones | B13: 7.0531
A14: Carne de res con hueso | B14: 1.7839
A15: Carne de res sin hueso | B15: 2.5879
A16: Carne de pollo | B16: 2.6813
A18: Pescados y mariscos | B18: 1.9813
A19: Pescado | B19: 1.3595
... A74: Uva | B74: 0.0772
B75: 0
A76: Frutas y vegetales en conservas | B76: 0.0224
A77: Jugo de naranja | B77: 0.0122
A78: Duraznos al jugo | B78: 0.0032
A79: Pasas | B79: 0.007
A81: Azúcar, sal y condimentos | B81: 1.6191
A82: Ajo | B82: 0.2635
A83: Azúcar | B83: 1.1201
A84: Panela | B84: 0.019
A85: Sal | B85: 0.1306
A86: Salsa de tomate | B86: 0.0859
A88: Café, te y bebidas gaseosas | B88: 1.2679
A89: Café molido | B89: 0.1171
... A286: Mantenimiento de automóvil (afinamiento, ABC) | B286: 0.2557
A291: regresar al índice

Sheet 4.18
A1: 4.18 CANASTA DE BIENES Y SERVICIOS PARA EL CÁLCULO DEL ÍNDICE DE
A2: PRECIOS AL CONSUMIDOR - COMPONENTES Y PONDERADORES -
A3: Base: enero-diciembre 2004
A5: ALIMENTOS Y BEBIDAS | B5: 32.253569
A7: Cereales y derivados | B7: 4.3121657
A8: arroz flor | B8: 1.5957175
A9: avena | B9: 0.1552767
A10: cereales preparados | B10: 0.065044
A11: fideos | B11: 0.2587467
A12: galletas | B12: 0.1302281
A13: harina de trigo | B13: 0.1000828
A14: maiz | B14: 0.0406034
A15: pan baguette | B15: 0.0630404
A16: pan corriente | B16: 1.8707432
A17: tallarines | B17: 0.0326829
... A386: neumáticos | B386: 0.2749558
A391: regresar al índice

Sheet 4.18.a
A1: 4.18.a CANASTA DE BIENES Y SERVICIOS PARA EL CÁLCULO DEL ÍNDICE DE
A2: PRECIOS AL CONSUMIDOR - COMPONENTES Y PONDERADORES -
A3: Base: enero-diciembre 2014
A5: ALIMENTOS Y BEBIDAS | B5: 30.674751
A7: Cereales y derivados | B7: 3.9444215
A8: arroz | B8: 1.5467425
A9: avena | B9: 0.078428454
A10: cereales enteros | B10: 0.049191259
A11: cereales preparados | B11: 0.095312935
A12: galletas | B12: 0.178756
A13: harina de otros cereales | B13: 0.043877345
A14: harina de trigo | B14: 0.072159826
A15: pan corriente | B15: 1.5779653
A16: pan envasado | B16: 0.053690336
A17: pan especial | B17: 0.017813257
... A446: servicio de wincha | B446: 0.034940328
A451: regresar al índice

Sheet 4.19
A1: 4.19 INDICADORES DEL MERCADO LABORAL ECUATORIANO.
A2: TOTAL NACIONAL (1) 2007-2016
A4: AÑO | B4: Tasas de
B5: Empleo Global | C5: Empleo Adecuado/Pleno | D5: Subempleo | E5: Otro Empleo No pleno | F5: Empleo No remunerado | G5: Empleo No clasificado | H5: Desempleo | I5: Desempleo Abierto | J5: Desempleo Oculto
A7: 2007 | B7: 0.95001645 | C7: 0.43199902 | D7: 0.1824284 | E7: 0.23737272 | F7: 0.087933051 | G7: 0.010283264 | H7: 0.049983546 | I7: 0.030496204 | J7: 0.019487342
A8: 2008 | B8: 0.94048537 | C8: 0.44768522 | D8: 0.15002587 | E8: 0.25829925 | F8: 0.082050636 | G8: 0.0024243977 | H8: 0.05951463 | I8: 0.03960967 | J8: 0.01990496
A9: 2009 | B9: 0.9352869 | C9: 0.39177209 | D9: 0.16363193 | E9: 0.27158275 | F9: 0.088900508 | G9: 0.019399623 | H9: 0.0647131 | I9: 0.044982826 | J9: 0.019730274
A10: 2010 | B10: 0.94981142 | C10: 0.44677099 | D10: 0.13816341 | E10: 0.27433454 | F10: 0.082189306 | G10: 0.0083531731 | H10: 0.05018858 | I10: 0.034888771 | J10: 0.015299809
A11: 2011 | B11: 0.9579454 | C11: 0.45529297 | D11: 0.107338 | E11: 0.31251796 | F11: 0.07680241 | G11: 0.0059940736 | H11: 0.042054597 | I11: 0.029806993 | J11: 0.012247605
A12: 2012 | B12: 0.95878622 | C12: 0.46532866 | D12: 0.090119229 | E12: 0.30123528 | F12: 0.080201414 | G12: 0.021901637 | H12: 0.04121378 | I12: 0.031364424 | J12: 0.0098493564
A13: 2013 | B13: 0.95847179 | C13: 0.47865018 | D13: 0.11639159 | E13: 0.29041901 | F13: 0.070930896 | G13: 0.0020801172 | H13: 0.041528209 | I13: 0.029501953 | J13: 0.012026256
A14: 2014 | B14: 0.96199694 | C14: 0.49284753 | D14: 0.12867761 | E14: 0.2675139 | F14: 0.0706755 | G14: 0.0022824096 | H14: 0.038003057 | I14: 0.030153682 | J14: 0.0078493752
A15: 2015 | B15: 0.95227165 | C15: 0.46503926 | D15: 0.14011363 | E15: 0.2642125 | F15: 0.076556542 | G15: 0.0063497184 | H15: 0.047728349 | I15: 0.036665725 | J15: 0.011062624
A16: 2016 | B16: 0.94787397 | C16: 0.411898 | D16: 0.19873267 | E16: 0.25121479 | F16: 0.083933393 | G16: 0.0020951166 | H16: 0.052126029 | I16: 0.040840831 | J16: 0.011285199
A19: 1) Datos a Diciembre de cada año
A21: regresar al índice

Sheet 4.20
A1: 4.20 INDICADORES DEL MERCADO LABORAL ECUATORIANO. (Anterior metodología)
A2: TOTAL URBANO (1) 1998-2014
A4: AÑO | B4: Tasas de
B5: Ocupación Total | C5: Ocupación Plena | D5: Subocupación Total | E5: Desocupación Total | F5: Desocupación Abierta | G5: Desocupación Oculta
A7: 1991 | B7: 0.9153287 | D7: 0.48730631 | E7: 0.084671299
A8: 1992 | B8: 0.91097498 | D8: 0.50727655 | E8: 0.089025016
A9: 1993 | B9: 0.91671485 | C9: 0.32417684 | D9: 0.50360383 | E9: 0.083285149 | F9: 0.063659289 | G9: 0.01962586
A10: 1994 | B10: 0.92868051 | C10: 0.35771873 | D10: 0.48145223 | E10: 0.071319486 | F10: 0.053829671 | G10: 0.017489815
A11: 1995 | B11: 0.93149694 | C11: 0.359971 | D11: 0.48315505 | E11: 0.068503057 | F11: 0.053814144 | G11: 0.014688914
A12: 1996 | B12: 0.89621202 | C12: 0.35412706 | D12: 0.4562451 | E12: 0.10378798 | F12: 0.083248848 | G12: 0.020539136
A13: 1997 | B13: 0.9076341 | C13: 0.38840273 | D13: 0.42805997 | E13: 0.092365901 | F13: 0.071356715 | G13: 0.021009185
A14: 1998 | B14: 0.88504906 | C14: 0.33004361 | D14: 0.42295373 | E14: 0.11495094 | F14: 0.086895209 | G14: 0.028055736
A15: 1999 | B15: 0.85583199 | C15: 0.27047754 | D15: 0.58535392 | E15: 0.14416801 | F15: 0.1008701 | G15: 0.043297385
A16: 2000 | B16: 0.91018922 | C16: 0.30487694 | D16: 0.60531255 | E16: 0.089810781 | F16: 0.059092206 | G16: 0.030718306
A17: 2001(2) | B17: 0.89065737 | C17: 0.33257496 | D17: 0.55808266 | E17: 0.10934263 | F17: 0.058816013 | G17: 0.050526128
A18: 2002 | B18: 0.90759361 | C18: 0.36965396 | D18: 0.53792624 | E18: 0.092403756 | F18: 0.054604969 | G18: 0.037799312
A19: 2003 | B19: 0.88450282 | C19: 0.33564412 | D19: 0.5488592 | E19: 0.11549593 | F19: 0.077006468 | G19: 0.038489959
A20: 2004 | B20: 0.91421595 | C20: 0.37242887 | D20: 0.54178732 | E20: 0.085783809 | F20: 0.058084969 | G20: 0.027699077
A21: 2005 | B21: 0.92105332 | C21: 0.36140448 | D21: 0.55964884 | E21: 0.078946682 | F21: 0.052519501 | G21: 0.026427181
A22: 2006 | B22: 0.92184384 | C22: 0.35509877 | D22: 0.56674506 | E22: 0.078156164 | F22: 0.04930798 | G22: 0.028848184
A23: 2007(3) | B23: 0.93934507 | C23: 0.42641319 | D23: 0.50228079 | E23: 0.060654928 | F23: 0.03963251 | G23: 0.021022418
A24: 2008 | B24: 0.92690165 | C24: 0.43590758 | D24: 0.48780266 | E24: 0.073098354 | F24: 0.052168211 | G24: 0.020930143
A25: 2009 | B25: 0.92072321 | C25: 0.38831751 | D25: 0.50477659 | E25: 0.079276791 | F25: 0.060245812 | G25: 0.019030979
A26: 2010 | B26: 0.93891064 | C26: 0.45602771 | D26: 0.47126994 | E26: 0.061089356 | F26: 0.045115947 | G26: 0.015973409
A27: 2011 | B27: 0.94933295 | C27: 0.49901803 | D27: 0.44220431 | E27: 0.050667053 | F27: 0.038763773 | G27: 0.01190328
A28: 2012 | B28: 0.94960016 | C28: 0.52067678 | D28: 0.39830836 | E28: 0.050399845 | F28: 0.039929611 | G28: 0.010470234
A29: 2013 | B29: 0.95142397 | C29: 0.51506232 | D29: 0.43349248 | E29: 0.048576032 | F29: 0.036823435 | G29: 0.011752597
A30: 2014 | B30: 0.95458355 | C30: 0.51398539 | D30: 0.43777202 | E30: 0.045416452 | F30: 0.037050834 | G30: 0.0083656177
A33: 1) Datos a Diciembre/ Noviembre de cada año.
A34: 2) Dato para agosto.
A35: 3) Los datos para después del 2007 corresponden a una nueva metodología.
A37: regresar al índice

Sheet 4.21
A1: 4.21 PRODUCCIÓN NACIONAL DE PETRÓLEO (1972-2016)
A2: Miles de barriles
A4: AÑOS | B4: Producción Empresas Públicas | F4: Produc. Cías. Privadas | G4: Total Producción Nacional
B5: EP Petroecuador (1) (2) | C5: Petroamazonas EP (2) | D5: Operadora Río Napo (3) | E5: TOTAL
A7: 1972 | B7: 28578 | C7: 0 | D7: 0 | E7: 28578 | F7: 0 | G7: 28578
A8: 1973 | B8: 76221 | C8: 0 | D8: 0 | E8: 76221 | F8: 0 | G8: 76221
A9: 1974 | B9: 64615 | C9: 0 | D9: 0 | E9: 64615 | F9: 0 | G9: 64615
A10: 1975 | B10: 58732 | C10: 0 | D10: 0 | E10: 58732 | F10: 0 | G10: 58732
A11: 1976 | B11: 68267 | C11: 0 | D11: 0 | E11: 68267 | F11: 0 | G11: 68267
A12: 1977 | B12: 66598 | C12: 0 | D12: 0 | E12: 66598 | F12: 0 | G12: 66598
A13: 1978 | B13: 72863 | C13: 0 | D13: 0 | E13: 72863 | F13: 791 | G13: 73654
A14: 1979 | B14: 76986 | C14: 0 | D14: 0 | E14: 76986 | F14: 1197 | G14: 78183
A15: 1980 | B15: 73146 | C15: 0 | D15: 0 | E15: 73146 | F15: 1476 | G15: 74622
A16: 1981 | B16: 75283 | C16: 0 | D16: 0 | E16: 75283 | F16: 1415 | G16: 76698
A17: 1982 | B17: 75760 | C17: 0 | D17: 0 | E17: 75760 | F17: 1241 | G17: 77001
A18: 1983 | B18: 85003 | C18: 0 | D18: 0 | E18: 85003 | F18: 1375 | G18: 86378
... A51: 2016 | B51: 0 | C51: 142668.7 | D51: 15449.68 | E51: 158118.38 | F51: 42593.034 | G51: 200711.41
A55: Notas
A56: regresar al índice

Sheet 4.22
A1: 4.22 EXPORTACIONES (1972-2016)
A2: Miles de barriles
A4: AÑOS | B4: Exportación de las Empresas Publicas | K4: Exportaciones de las Cías. Privadas | N4: Secretaría de Hidrocarburos
B5: Crudo Oriente | E5: Crudo Napo (1) | H5: Total Exportaciones de las Empresas Públicas (2) | K5: Compañías Privadas | N5: Servicios Cías. Privadas (3)
B6: Barriles | C6: USD FOB | D6: Valor unitario dólares/barril | E6: Barriles | F6: USD FOB | G6: Valor unitario dólares/barril | H6: Barriles | I6: USD FOB | J6: Valor unitario dólares/barril | K6: Barriles | L6: USD FOB | M6: Valor unitario dólares/barril | N6: Barriles | O6: USD FOB | P6: Valor unitario dólares/barril
A8: 1972 | B8: 24961.6 | C8: 62404 | D8: 2.5 | E8: 0 | F8: 0 | G8: 0 | H8: 24961.6 | I8: 62404 | J8: 2.5 | K8: 0 | L8: 0 | M8: 0 | N8: 0 | O8: 0 | P8: 0
A9: 1973 | B9: 71125.6 | C9: 298727.6 | D9: 4.2000011 | E9: 0 | F9: 0 | G9: 0 | H9: 71125.6 | I9: 298727.6 | J9: 4.2000011 | K9: 0 | L9: 0 | M9: 0 | N9: 0 | O9: 0 | P9: 0
A10: 1974 | B10: 59233.1 | C10: 772065.9 | D10: 13.034366 | E10: 0 | F10: 0 | G10: 0 | H10: 59233.1 | I10: 772065.9 | J10: 13.034366 | K10: 0 | L10: 0 | M10: 0 | N10: 0 | O10: 0 | P10: 0
A11: 1975 | B11: 52267.9 | C11: 601081 | D11: 11.500003 | E11: 0 | F11: 0 | G11: 0 | H11: 52267.9 | I11: 601081 | J11: 11.500003 | K11: 0 | L11: 0 | M11: 0 | N11: 0 | O11: 0 | P11: 0
A12: 1976 | B12: 61336.9 | C12: 648647.3 | D12: 10.575156 | E12: 0 | F12: 0 | G12: 0 | H12: 61336.9 | I12: 648647.3 | J12: 10.575156 | K12: 0 | L12: 0 | M12: 0 | N12: 0 | O12: 0 | P12: 0
A13: 1977 | B13: 50453.1 | C13: 655890.3 | D13: 13 | E13: 0 | F13: 0 | G13: 0 | H13: 50453.1 | I13: 655890.3 | J13: 13 | K13: 0 | L13: 0 | M13: 0 | N13: 0 | O13: 0 | P13: 0
A14: 1978 | B14: 44487.1 | C14: 556088.8 | D14: 12.500001 | E14: 0 | F14: 0 | G14: 0 | H14: 44487.1 | I14: 556088.8 | J14: 12.500001 | K14: 312 | L14: 3900 | M14: 12.5 | N14: 0 | O14: 0 | P14: 0
A15: 1979 | B15: 44447 | C15: 953276.2 | D15: 21.447481 | E15: 0 | F15: 0 | G15: 0 | H15: 44447 | I15: 953276.2 | J15: 21.447481 | K15: 344.2 | L15: 8088.7 | M15: 23.5 | N15: 0 | O15: 0 | P15: 0
A16: 1980 | B16: 39187.6 | C16: 1361133.9 | D16: 34.733791 | E16: 0 | F16: 0 | G16: 0 | H16: 39187.6 | I16: 1361133.9 | J16: 34.733791 | K16: 448.7 | L16: 15821.2 | M16: 35.260085 | N16: 0 | O16: 0 | P16: 0
A17: 1981 | B17: 45068.9 | C17: 1553842.3 | D17: 34.477041 | E17: 0 | F17: 0 | G17: 0 | H17: 45068.9 | I17: 1553842.3 | J17: 34.477041 | K17: 379.8 | L17: 13095.5 | M17: 34.479989 | N17: 0 | O17: 0 | P17: 0
A18: 1982 | B18: 41695.6 | C18: 1156257.8 | D18: 27.730931 | E18: 0 | F18: 0 | G18: 0 | H18: 41695.6 | I18: 1156257.8 | J18: 27.730931 | K18: 430 | L18: 14121.2 | M18: 32.84 | N18: 0 | O18: 0 | P18: 0
A19: 1983 | B19: 58822.7 | C19: 1514489.4 | D19: 25.746683 | E19: 0 | F19: 0 | G19: 0 | H19: 58822.7 | I19: 1514489.4 | J19: 25.746683 | K19: 480 | L19: 13478.4 | M19: 28.08 | N19: 0 | O19: 0 | P19: 0
... A52: 2016 | B52: 81532.408 | C52: 3030671.4 | D52: 37.171371 | E52: 44469.292 | F52: 1410458.4 | G52: 31.717581 | H52: 126001.7 | I52: 4441129.7 | J52: 35.246586 | K52: 0 | L52: 0 | M52: 0 | N52: 18557.685 | O52: 612806.48 | P52: 33.021709
A56: Notas
A57: regresar al índice

Sheet 4.23
A1: 4.23 CRUDO TRANSPORTADO POR OLEODUCTOS (1972-2016)
A2: Miles de barriles
A4: AÑOS | B4: Total S.O.T.E. (1) | C4: Total O.T.A. (2) | D4: Total O.C.P. (3) | E4: TOTAL
A6: 1972 | B6: 27408 | C6: 0 | D6: 0 | E6: 27408
A7: 1973 | B7: 75152 | C7: 0 | D7: 0 | E7: 75152
A8: 1974 | B8: 63695 | C8: 0 | D8: 0 | E8: 63695
A9: 1975 | B9: 57957 | C9: 0 | D9: 0 | E9: 57957
A10: 1976 | B10: 67373 | C10: 0 | D10: 0 | E10: 67373
A11: 1977 | B11: 65909 | C11: 0 | D11: 0 | E11: 65909
A12: 1978 | B12: 72994 | C12: 0 | D12: 0 | E12: 72994
A13: 1979 | B13: 77518 | C13: 0 | D13: 0 | E13: 77518
A14: 1980 | B14: 74014 | C14: 0 | D14: 0 | E14: 74014
A15: 1981 | B15: 76228 | C15: 0 | D15: 0 | E15: 76228
A16: 1982 | B16: 76379 | C16: 0 | D16: 0 | E16: 76379
A17: 1983 | B17: 86171 | C17: 0 | D17: 0 | E17: 86171
... A50: 2016 | B50: 132890.96 | C50: 0 | D50: 61172.388 | E50: 194063.34
A54: Notas
A55: regresar al índice

Sheet 4.24
A1: 4.24 PRODUCCIÓN NACIONAL DE DERIVADOS 1972-2016 (1)
A2: Miles de Barriles
A4: AÑOS | B4: GASOLINAS | H4: G.L.P. | I4: NAFTA D | J4: ABSORVER OIL | K4: DIESEL 1 (2) | L4: DIESEL 2 | M4: DIESEL PREMIUM | N4: FUEL OIL # 4 (3) | O4: Residuo Termoesmeraldas REE | P4: COMBUSTIBLE MEZCLA ( 4 ) | Q4: CRUDO REDUCIDO REF. AMAZONAS ( 5 ) | R4: JET FUEL | S4: SPRAY OIL | T4: ASFALTOS | U4: SOLVENTES | V4: NAFTA BASE 90 | W4: PESCA ARTESA- NAL | X4: GASOLINA NATURAL | Y4: TOTAL
B5: SUPER | C5: ECO-82/85 | D5: Extra con Etanol (ECOPAIS) | E5: EXTRA | F5: REGULAR | G5: TOTAL
A7: 1972 | B7: 0 | C7: 0 | D7: 0 | E7: 2301.964 | F7: 1270.084 | G7: 3572.048 | H7: 50.406 | I7: 0 | J7: 0 | K7: 417.11 | L7: 2234.68 | M7: 0 | N7: 2877.665 | O7: 0 | P7: 0 | Q7: 0 | R7: 796.915 | S7: 159.326 | T7: 0 | U7: 11.401 | V7: 0 | W7: 0 | X7: 0 | Y7: 10119.551
A8: 1973 | B8: 0 | C8: 0 | D8: 0 | E8: 2790.085 | F8: 1273.307 | G8: 4063.392 | H8: 49.992 | I8: 0 | J8: 0 | K8: 399.509 | L8: 2606.171 | M8: 0 | N8: 3013.32 | O8: 0 | P8: 0 | Q8: 0 | R8: 911.384 | S8: 169.587 | T8: 0 | U8: 16.433 | V8: 0 | W8: 0 | X8: 0 | Y8: 11229.788
A9: 1974 | B9: 0 | C9: 0 | D9: 0 | E9: 3544.225 | F9: 1254.189 | G9: 4798.414 | H9: 63.187 | I9: 0 | J9: 0 | K9: 564.646 | L9: 2869.195 | M9: 0 | N9: 3067.124 | O9: 0 | P9: 0 | Q9: 0 | R9: 918.421 | S9: 86.452 | T9: 0 | U9: 15.186 | V9: 0 | W9: 0 | X9: 0 | Y9: 12382.625
A10: 1975 | B10: 0 | C10: 0 | D10: 0 | E10: 4280.476 | F10: 1368.466 | G10: 5648.942 | H10: 52.768 | I10: 0 | J10: 0 | K10: 1429.006 | L10: 3046.854 | M10: 0 | N10: 3410.8 | O10: 0 | P10: 0 | Q10: 0 | R10: 460.839 | S10: 127.254 | T10: 0 | U10: 15.53 | V10: 0 | W10: 0 | X10: 0 | Y10: 14191.993
A11: 1976 | B11: 0 | C11: 0 | D11: 0 | E11: 4833.45 | F11: 1212.867 | G11: 6046.317 | H11: 40.087 | I11: 0 | J11: 0 | K11: 1914.283 | L11: 2787.051 | M11: 0 | N11: 3604.874 | O11: 0 | P11: 0 | Q11: 0 | R11: 453.977 | S11: 131.626 | T11: 0 | U11: 19.94 | V11: 0 | W11: 0 | X11: 0 | Y11: 14998.155
A12: 1977 | B12: 0 | C12: 0 | D12: 0 | E12: 5297.134 | F12: 811.032 | G12: 6108.166 | H12: 227.933 | I12: 0 | J12: 0 | K12: 2448.406 | L12: 3127.157 | M12: 0 | N12: 6432.511 | O12: 0 | P12: 0 | Q12: 0 | R12: 433.257 | S12: 97.91 | T12: 208.01 | U12: 30.959 | V12: 0 | W12: 0 | X12: 0 | Y12: 19114.309
A13: 1978 | B13: 0 | C13: 0 | D13: 0 | E13: 6605.543 | F13: 646.817 | G13: 7252.36 | H13: 715.836 | I13: 0 | J13: 0 | K13: 2659.737 | L13: 4440.249 | M13: 0 | N13: 12824.587 | O13: 0 | P13: 0 | Q13: 0 | R13: 933.061 | S13: 63.663 | T13: 415.16 | U13: 39.663 | V13: 0 | W13: 0 | X13: 0 | Y13: 29344.316
A14: 1979 | B14: 0 | C14: 0 | D14: 0 | E14: 7448.353 | F14: 670.853 | G14: 8119.206 | H14: 809.951 | I14: 0 | J14: 0 | K14: 2230.315 | L14: 4998.051 | M14: 0 | N14: 13844.319 | O14: 0 | P14: 0 | Q14: 0 | R14: 1095.567 | S14: 70.18 | T14: 287.291 | U14: 41.313 | V14: 0 | W14: 0 | X14: 0 | Y14: 31496.193
A15: 1980 | B15: 145.713 | C15: 0 | D15: 0 | E15: 7665.538 | F15: 586.489 | G15: 8397.74 | H15: 842.527 | I15: 0 | J15: 0 | K15: 2272.216 | L15: 5529.236 | M15: 0 | N15: 14977.163 | O15: 0 | P15: 0 | Q15: 0 | R15: 1071.907 | S15: 79.302 | T15: 304.981 | U15: 49.428 | V15: 0 | W15: 0 | X15: 0 | Y15: 33524.5
A16: 1981 | B16: 395.577 | C16: 0 | D16: 0 | E16: 6834.779 | F16: 529.057 | G16: 7759.413 | H16: 665.538 | I16: 0 | J16: 0 | K16: 2206.726 | L16: 4957.737 | M16: 0 | N16: 14614.275 | O16: 0 | P16: 0 | Q16: 0 | R16: 1094.762 | S16: 62.279 | T16: 305.684 | U16: 48.64 | V16: 0 | W16: 0 | X16: 0 | Y16: 31715.054
A17: 1982 | B17: 559.069 | C17: 0 | D17: 0 | E17: 7016.221 | F17: 704.509 | G17: 8279.799 | H17: 755.625 | I17: 0 | J17: 0 | K17: 2531.729 | L17: 5151.66 | M17: 0 | N17: 14491.226 | O17: 0 | P17: 0 | Q17: 0 | R17: 1051.808 | S17: 65.224 | T17: 343.585 | U17: 56.079 | V17: 0 | W17: 0 | X17: 45.285 | Y17: 32772.02
A18: 1983 | B18: 296.722 | C18: 0 | D18: 0 | E18: 5413.746 | F18: 526.317 | G18: 6236.785 | H18: 642.246 | I18: 0 | J18: 0 | K18: 2063.069 | L18: 4201.004 | M18: 0 | N18: 12355.472 | O18: 0 | P18: 0 | Q18: 0 | R18: 876.154 | S18: 117.679 | T18: 265.011 | U18: 51.579 | V18: 0 | W18: 0 | X18: 74.806 | Y18: 26883.805
... A28: 1993 | B28: 492.578 | C28: 20.109 | D28: 0 | E28: 10439.655 | F28: 5.371 | G28: 10957.713 | H28: 2966.381 | I28: 0 | J28: 0 | K28: 646.334 | L28: 10986.08 | M28: 0 | N28: 15632.046 | O28: 0 | P28: 0 | Q28: 1481.959 | R28: 1466.362 | S28: 177.535 | T28: 488.041 | U28: 99.613 | V28: 0 | W28: 0 | X28: 462.479 | Y28: 45364.543
A29: 1994 (l) | B29: 525.708 | C29: 513.772 | D29: 0 | E29: 10006.032 | F29: 0 | G29: 11045.512 | H29: 2951.41 | I29: 0 | J29: 0 | K29: 552.637 | L29: 11090.399 | M29: 0 | N29: 18121.103 | O29: 0 | P29: 0 | Q29: 1597.838 | R29: 1355.113 | S29: 155.878 | T29: 635.784 | U29: 100.123 | V29: 0 | W29: 0 | X29: 409.064 | Y29: 48014.861
A30: 1995 | B30: 696.448 | C30: 1370.006 | D30: 0 | E30: 8426.356 | F30: 0 | G30: 10492.81 | H30: 2405.743 | I30: 0 | J30: 0 | K30: 594.036 | L30: 10363.746 | M30: 0 | N30: 8845.004 | O30: 0 | P30: 10614.272 | Q30: 2305.011 | R30: 1602.083 | S30: 181.434 | T30: 616.611 | U30: 97.25 | V30: 0 | W30: 346.538 | X30: 461.759 | Y30: 48926.297
A31: 1996 | B31: 851.737 | C31: 1916.711 | D31: 0 | E31: 8083.129 | F31: 0 | G31: 10851.577 | H31: 2950.489 | I31: 2995.427 | J31: 1.702 | K31: 519.484 | L31: 12137.558 | M31: 0 | N31: 9029.044 | O31: 0 | P31: 12511.902 | Q31: 3226.056 | R31: 1694.893 | S31: 140.649 | T31: 626.53 | U31: 99.311 | V31: 0 | W31: 278.248 | X31: 545.674 | Y31: 57608.544
A32: 1997 | B32: 984.715 | C32: 2163.869 | D32: 0 | E32: 7752.69 | F32: 0 | G32: 10901.274 | H32: 2309.688 | I32: 1896.152 | J32: 3.889 | K32: 639.872 | L32: 8879.093 | M32: 0 | N32: 10557.338 | O32: 0 | P32: 9122.955 | Q32: 3168.726 | R32: 1959.908 | S32: 176.022 | T32: 530.087 | U32: 104.656 | V32: 0 | W32: 0.612 | X32: 593.33 | Y32: 50843.602
A33: 1998 | B33: 1424.016 | C33: 472.911 | D33: 0 | E33: 9135.012 | F33: 0 | G33: 11031.939 | H33: 2453.172 | I33: 2235.149 | J33: 2.301 | K33: 826.63 | L33: 8950.384 | M33: 0 | N33: 10044.773 | O33: 0 | P33: 11585.871 | Q33: 3026.825 | R33: 2027.051 | S33: 128.185 | T33: 824.777 | U33: 140.516 | V33: 0 | W33: 0 | X33: 629.366 | Y33: 53906.939
A34: 1999 | B34: 1714.066 | C34: 0 | D34: 0 | E34: 9669.827 | F34: 0 | G34: 11383.893 | H34: 2014.455 | I34: 2001.252 | J34: 1.272 | K34: 731.273 | L34: 7001.09 | M34: 1079.897 | N34: 9876.939 | O34: 0 | P34: 10948.854 | Q34: 2489.344 | R34: 1518.845 | S34: 67.984 | T34: 700.282 | U34: 77.82 | V34: 174.652 | W34: 48.274 | X34: 621.437 | Y34: 50737.563
A35: 2000 | B35: 3080.963 | C35: 0 | D35: 0 | E35: 10282.987 | F35: 0 | G35: 13363.95 | H35: 2817.665 | I35: 2070.101 | J35: 1.307 | K35: 574.365 | L35: 10433.558 | M35: 1646.568 | N35: 10786.691 | O35: 0 | P35: 14078.769 | Q35: 2484.372 | R35: 1937.964 | S35: 35.265 | T35: 809.828 | U35: 104.236 | V35: 64.374 | W35: 273.094 | X35: 679.043 | Y35: 62161.15
A36: 2001 | B36: 1399.516 | C36: 0 | D36: 0 | E36: 10837.158 | F36: 0 | G36: 12236.674 | H36: 2406.524 | I36: 1757.883 | J36: 1.092 | K36: 596.655 | L36: 12911.06 | M36: 539.298 | N36: 10953.26 | O36: 0 | P36: 11898.357 | Q36: 2467.367 | R36: 1771.467 | S36: 65.326 | T36: 1064.879 | U36: 77.663 | V36: 253.496 | W36: 275.506 | X36: 645.74 | Y36: 59922.247
A37: 2002 | B37: 2723.915 | C37: 0 | D37: 0 | E37: 10163.265 | F37: 0 | G37: 12887.18 | H37: 2060.016 | I37: 1940.024 | J37: 1.874 | K37: 536.432 | L37: 11978.511 | M37: 460.165 | N37: 11353.764 | O37: 0 | P37: 10741.979 | Q37: 2719.97 | R37: 1797.434 | S37: 73.178 | T37: 1086.604 | U37: 60.997 | V37: 209.186 | W37: 279.654 | X37: 582.287 | Y37: 58769.255
A38: 2003 | B38: 3062.401 | C38: 0 | D38: 0 | E38: 10027.961 | F38: 0 | G38: 13090.362 | H38: 2229.989 | I38: 2585.075 | J38: 1.604 | K38: 515.84 | L38: 10961.17 | M38: 87.521 | N38: 10811.957 | O38: 0 | P38: 8878.82 | Q38: 2620.108 | R38: 1878.822 | S38: 49.219 | T38: 1199.999 | U38: 20.709 | V38: 89.199 | W38: 295.432 | X38: 501.536 | Y38: 55817.362
A39: 2004 | B39: 2762.631 | C39: 0 | D39: 0 | E39: 10312.056 | F39: 0 | G39: 13074.687 | H39: 2184.076 | I39: 2551.09 | J39: 1.496 | K39: 549.147 | L39: 11866.037 | M39: 801.356 | N39: 11267.071 | O39: 0 | P39: 10011.509 | Q39: 2861.166 | R39: 2209.198 | S39: 85.908 | T39: 1158.288 | U39: 38.281 | V39: 159.402 | W39: 320.218 | X39: 539.227 | Y39: 59678.157
A40: 2005 | B40: 3101.349 | C40: 0 | D40: 0 | E40: 10628.413 | F40: 0 | G40: 13729.762 | H40: 2119.665 | I40: 2108.911 | J40: 0.199 | K40: 462.426 | L40: 12458.755 | M40: 110.449 | N40: 11850.989 | O40: 0 | P40: 10474.185 | Q40: 3243.031 | R40: 2461.215 | S40: 101.897 | T40: 989.858 | U40: 54.988 | V40: 608.406 | W40: 387.687 | X40: 458.05 | Y40: 61620.473
A41: 2006 | B41: 3244.0936 | C41: 0 | D41: 0 | E41: 10252.348 | F41: 0 | G41: 13496.442 | H41: 1943.774 | I41: 1691.394 | J41: 0 | K41: 257.322 | L41: 11025.173 | M41: 191.741 | N41: 8826.9538 | O41: 940.57319 | P41: 10970.776 | Q41: 3018.085 | R41: 2394.74 | S41: 123.8 | T41: 896.129 | U41: 78.506 | V41: 791.314 | W41: 415.23207 | X41: 339.434 | Y41: 57401.389
... A51: 2016 | B51: 5209.4075 | C51: 0 | D51: 5156.947 | E51: 17624.251 | F51: 0 | G51: 27990.606 | H51: 2872.1238 | I51: 521.33216 | J51: 0.476 | K51: 124.70344 | L51: 5795.2834 | M51: 7206.9297 | N51: 6872.0794 | O51: 3311.2059 | P51: 11438.746 | Q51: 3277.1557 | R51: 2687.1781 | S51: 65.89165 | T51: 1456.8407 | U51: 143.49468 | V51: 25.183571 | W51: 784.53568 | X51: 0 | Y51: 74573.765
A55: Notas
A56: regresar al índice

Sheet 4.25
A1: 4.25 IMPORTACIÓN DE PRODUCTOS DERIVADOS DE PETRÓLEO REALIZADA POR EP PETROECUADOR 1972-2016
A2: Miles de barriles
A4: AÑOS | B4: GASOLINAS | D4: DIESEL | E4: GLP | F4: AVGAS | G4: JET FUEL (1) | H4: ASFALTOS y OTROS | I4: CUTTER STOCK | J4: MEZCLAS | K4: VGO | L4: GASOLEO | M4: TOTAL (2)
B5: 80-84 OCT. | C5: 92 0CT. | J5: PRODUCT.
A7: 1972 | B7: 0 | C7: 0 | D7: 0 | E7: 55.068 | F7: 117.644 | G7: 0 | H7: 0 | I7: 0 | J7: 0 | K7: 0 | L7: 0 | M7: 172.712
A8: 1973 | B8: 0 | C8: 0 | D8: 0 | E8: 99.949 | F8: 84.657 | G8: 0 | H8: 0 | I8: 0 | J8: 0 | K8: 0 | L8: 0 | M8: 184.606
A9: 1974 | B9: 0 | C9: 0 | D9: 0 | E9: 163.843 | F9: 76.131 | G9: 0 | H9: 0 | I9: 0 | J9: 0 | K9: 0 | L9: 0 | M9: 239.974
A10: 1975 | B10: 0 | C10: 0 | D10: 203.305 | E10: 250.436 | F10: 63.855 | G10: 0 | H10: 0 | I10: 0 | J10: 7193.194 | K10: 0 | L10: 0 | M10: 7710.79
A11: 1976 | B11: 258.846 | C11: 0 | D11: 828.561 | E11: 393.023 | F11: 47.263 | G11: 76.749 | H11: 226.486 | I11: 0 | J11: 7037.026 | K11: 0 | L11: 0 | M11: 8867.954
A12: 1977 | B12: 1679.279 | C12: 0 | D12: 1119.592 | E12: 371.45 | F12: 49.048 | G12: 443.006 | H12: 254.041 | I12: 0 | J12: 5173.276 | K12: 0 | L12: 0 | M12: 9089.692
A13: 1978 | B13: 1294.178 | C13: 0 | D13: 405.866 | E13: 99.318 | F13: 28.122 | G13: 292.608 | H13: 0 | I13: 0 | J13: 0 | K13: 0 | L13: 0 | M13: 2120.092
A14: 1979 | B14: 1356.054 | C14: 0 | D14: 840.257 | E14: 91.656 | F14: 50.936 | G14: 391.856 | H14: 0 | I14: 0 | J14: 0 | K14: 0 | L14: 0 | M14: 2730.759
A15: 1980 | B15: 2516.053 | C15: 0 | D15: 1323.36 | E15: 316.42 | F15: 39.725 | G15: 396.412 | H15: 0 | I15: 0 | J15: 0 | K15: 0 | L15: 0 | M15: 4591.97
A16: 1981 | B16: 2735.658 | C16: 0 | D16: 1970.641 | E16: 654.73 | F16: 21.166 | G16: 0 | H16: 0 | I16: 0 | J16: 0 | K16: 0 | L16: 0 | M16: 5382.195
A17: 1982 | B17: 2658.184 | C17: 52.203 | D17: 2067.936 | E17: 733.542 | F17: 30.31 | G17: 29.989 | H17: 0 | I17: 0 | J17: 0 | K17: 0 | L17: 0 | M17: 5572.164
A18: 1983 | B18: 3341.425 | C18: 0 | D18: 2545.473 | E18: 970.361 | F18: 40.001 | G18: 11.769 | H18: 0 | I18: 0 | J18: 0 | K18: 0 | L18: 0 | M18: 6909.029
... A51: 2016 | B51: 0 | C51: 15943.833 | D51: 18053.043 | E51: 9835.3175 | F51: 33.4521 | G51: 0 | H51: 0 | I51: 3182.2693 | J51: 0 | K51: 0 | L51: 0 | M51: 47047.915
A55: Notas
A56: regresar al índice

Sheet 4.26
A1: 4.26 VENTA NACIONAL DE DERIVADOS 1972-2016 (1)
A2: Miles de Barriles
A4: AÑOS | B4: GASOLINAS (2) | H4: DIESEL | I4: DIESEL 1 | L4: DIESEL 2 | U4: FUEL OIL | AC4: SOLVENTES | AH4: AVGAS | AK4: JET FUEL | AN4: TURBO FUEL | AO4: KEREX | AP4: ABSORVER | AQ4: ASFALTO | AR4: GLP | AS4: SPRAY OIL | AT4: AERO-COMBUSTIBLE | AU4: LUBRICANTES | AV4: NAFTA BASE 90 (Sector Eléctrico) | AW4: NAFTA BASE | AX4: PESCA ARTESANAL | AY4: RESIDUO | BC4: TOTAL
B5: SÚPER | C5: EXTRA | D5: EXTRA CON ETHANOL | E5: REGULAR | F5: ECO-85 | G5: TOTAL GASOLINAS | I5: TERRESTRE | J5: MARINO INTERN. | K5: TOTAL DIESEL 1 | L5: TERRESTRE | M5: PREMIUM | N5: ELÉCTRICO | O5: MARINO NACIONAL | P5: MARINO INTERNC. | Q5: DILUYENTE SECTOR ELÉCTRICO | R5: BUQUES CONTRATADOS CEPE | S5: PESQUERO | T5: TOTAL DIESEL 2 | U5: NACIONAL | V5: RESIDUO | W5: INDUSTRIAL | X5: MARINO | Y5: INTERNACIONAL | Z5: ELÉCTRICO | AA5: BUQUES CONTRATADOS CEPE | AB5: TOTAL FUEL OIL | AC5: MINERAL TURPENTINE | AD5: RUBBER SOLVENT | AE5: SOLVENTE N° 1 | AF5: STODDAR SOLVENT | AG5: TOTAL SOLVENTES | AH5: NACIONAL | AI5: INTERNACIONAL | AJ5: TOTAL AVGAS | AK5: NACIONAL | AL5: INTERNACIONAL | AM5: TOTAL JET FUEL | AY5: SECTOR ELECTRICO Ref. Amazonas | AZ5: INDUSTRIAL Ref. Amazonas | BA5: TERMO- ESMERALDAS Ref. Esmeraldas | BB5: RESIDUO
A7: 1972 | B7: 0 | C7: 2397.684 | D7: 0 | E7: 1307.578 | F7: 0 | G7: 3705.262 | H7: 2115.459 | I7: 0 | J7: 0 | K7: 0 | L7: 0 | M7: 0 | N7: 0 | O7: 0 | P7: 0 | Q7: 0 | R7: 0 | S7: 0 | T7: 0 | U7: 0 | V7: 2149.727 | W7: 0 | X7: 0 | Y7: 0 | Z7: 0 | AA7: 0 | AB7: 2149.727 | AC7: 3.034 | AD7: 2.693 | AE7: 2.603 | AF7: 3.195 | AG7: 11.525 | AH7: 126.29 | AI7: 0 | AJ7: 126.29 | AK7: 0 | AL7: 0 | AM7: 0 | AN7: 320.9949 | AO7: 936.965 | AP7: 0 | AQ7: 110.595 | AR7: 113.507 | AS7: 163.502 | AT7: 447.2849 | AU7: 0 | AV7: 0 | AW7: 0 | AX7: 0 | AY7: 0 | AZ7: 0 | BA7: 0 | BB7: 0 | BC7: 10201.112
A8: 1973 | B8: 0 | C8: 2835.6294 | D8: 0 | E8: 1289.7828 | F8: 0 | G8: 4125.4122 | H8: 2513.178 | I8: 0 | J8: 0 | K8: 0 | L8: 0 | M8: 0 | N8: 0 | O8: 0 | P8: 0 | Q8: 0 | R8: 0 | S8: 0 | T8: 0 | U8: 0 | V8: 2222.773 | W8: 0 | X8: 0 | Y8: 0 | Z8: 0 | AA8: 0 | AB8: 2222.773 | AC8: 4.853 | AD8: 3.338 | AE8: 3.323 | AF8: 3.717 | AG8: 15.231 | AH8: 92.265 | AI8: 0 | AJ8: 92.265 | AK8: 0 | AL8: 0 | AM8: 0 | AN8: 318.59505 | AO8: 1078.4787 | AP8: 0 | AQ8: 213.16 | AR8: 160.961 | AS8: 138.375 | AT8: 410.86005 | AU8: 0 | AV8: 0 | AW8: 0 | AX8: 0 | AY8: 0 | AZ8: 0 | BA8: 0 | BB8: 0 | BC8: 11289.289
A9: 1974 | B9: 0 | C9: 3498.5615 | D9: 0 | E9: 1234.7266 | F9: 0 | G9: 4733.2881 | H9: 2611.869 | I9: 0 | J9: 0 | K9: 0 | L9: 0 | M9: 0 | N9: 0 | O9: 0 | P9: 0 | Q9: 0 | R9: 0 | S9: 0 | T9: 0 | U9: 0 | V9: 2480.742 | W9: 0 | X9: 0 | Y9: 0 | Z9: 0 | AA9: 0 | AB9: 2480.742 | AC9: 5.648 | AD9: 4.144 | AE9: 3.773 | AF9: 0.357 | AG9: 13.922 | AH9: 76.682 | AI9: 0 | AJ9: 76.682 | AK9: 0 | AL9: 0 | AM9: 0 | AN9: 591.41 | AO9: 1198.7489 | AP9: 0 | AQ9: 320.187 | AR9: 218.335 | AS9: 117.083 | AT9: 668.092 | AU9: 0 | AV9: 0 | AW9: 0 | AX9: 0 | AY9: 0 | AZ9: 0 | BA9: 0 | BB9: 0 | BC9: 13030.359
A10: 1975 | B10: 0 | C10: 4442.718 | D10: 0 | E10: 1374.776 | F10: 0 | G10: 5817.494 | H10: 3209.803 | I10: 0 | J10: 0 | K10: 0 | L10: 0 | M10: 0 | N10: 0 | O10: 0 | P10: 0 | Q10: 0 | R10: 0 | S10: 0 | T10: 0 | U10: 0 | V10: 3040.376 | W10: 0 | X10: 0 | Y10: 0 | Z10: 0 | AA10: 0 | AB10: 3040.376 | AC10: 7.641 | AD10: 6.561 | AE10: 4.404 | AF10: 0 | AG10: 18.606 | AH10: 56.248 | AI10: 0 | AJ10: 56.248 | AK10: 0 | AL10: 0 | AM10: 0 | AN10: 747.042 | AO10: 1465.316 | AP10: 0 | AQ10: 410.223 | AR10: 290.895 | AS10: 117.869 | AT10: 803.29 | AU10: 0 | AV10: 0 | AW10: 0 | AX10: 0 | AY10: 0 | AZ10: 0 | BA10: 0 | BB10: 0 | BC10: 15977.162
A11: 1976 | B11: 0 | C11: 5323.916 | D11: 0 | E11: 1286.7 | F11: 0 | G11: 6610.616 | H11: 3617.456 | I11: 0 | J11: 0 | K11: 0 | L11: 0 | M11: 0 | N11: 0 | O11: 0 | P11: 0 | Q11: 0 | R11: 0 | S11: 0 | T11: 0 | U11: 0 | V11: 3162.453 | W11: 0 | X11: 0 | Y11: 0 | Z11: 0 | AA11: 0 | AB11: 3162.453 | AC11: 7.666 | AD11: 9.41 | AE11: 3.527 | AF11: 0 | AG11: 20.603 | AH11: 40.113 | AI11: 0 | AJ11: 40.113 | AK11: 0 | AL11: 0 | AM11: 0 | AN11: 378.542 | AO11: 2030.762 | AP11: 0 | AQ11: 480.945 | AR11: 389.305 | AS11: 121.337 | AT11: 418.655 | AU11: 0 | AV11: 0 | AW11: 0 | AX11: 0 | AY11: 0 | AZ11: 0 | BA11: 0 | BB11: 0 | BC11: 17270.787
A12: 1977 | B12: 0 | C12: 6569.284 | D12: 0 | E12: 927.341 | F12: 0 | G12: 7496.625 | H12: 4355.229 | I12: 0 | J12: 0 | K12: 0 | L12: 0 | M12: 0 | N12: 0 | O12: 0 | P12: 0 | Q12: 0 | R12: 0 | S12: 0 | T12: 0 | U12: 0 | V12: 3310.678 | W12: 0 | X12: 0 | Y12: 0 | Z12: 0 | AA12: 0 | AB12: 3310.678 | AC12: 11.657 | AD12: 11.181 | AE12: 6.302 | AF12: 0 | AG12: 29.14 | AH12: 46.657 | AI12: 0 | AJ12: 46.657 | AK12: 0 | AL12: 0 | AM12: 0 | AN12: 638.343 | AO12: 2484.537 | AP12: 0 | AQ12: 479.162 | AR12: 545.102 | AS12: 116.588 | AT12: 685 | AU12: 0 | AV12: 0 | AW12: 0 | AX12: 0 | AY12: 0 | AZ12: 0 | BA12: 0 | BB12: 0 | BC12: 20187.061
A13: 1978 | B13: 0 | C13: 7798.179 | D13: 0 | E13: 664.726 | F13: 0 | G13: 8462.905 | H13: 4676.479 | I13: 0 | J13: 0 | K13: 0 | L13: 0 | M13: 0 | N13: 0 | O13: 0 | P13: 0 | Q13: 0 | R13: 0 | S13: 0 | T13: 0 | U13: 0 | V13: 4232.205 | W13: 0 | X13: 0 | Y13: 0 | Z13: 0 | AA13: 0 | AB13: 4232.205 | AC13: 17.038 | AD13: 11.763 | AE13: 6.716 | AF13: 0 | AG13: 35.517 | AH13: 42.779 | AI13: 0 | AJ13: 42.779 | AK13: 0 | AL13: 0 | AM13: 0 | AN13: 935.649 | AO13: 2834.21 | AP13: 0 | AQ13: 168.485 | AR13: 722.26 | AS13: 43.58 | AT13: 978.428 | AU13: 0 | AV13: 0 | AW13: 0 | AX13: 0 | AY13: 0 | AZ13: 0 | BA13: 0 | BB13: 0 | BC13: 23132.497
A14: 1979 | B14: 0 | C14: 8862.608 | D14: 0 | E14: 664.476 | F14: 0 | G14: 9527.084 | H14: 5514.064 | I14: 0 | J14: 0 | K14: 0 | L14: 0 | M14: 0 | N14: 0 | O14: 0 | P14: 0 | Q14: 0 | R14: 0 | S14: 0 | T14: 0 | U14: 0 | V14: 5095.089 | W14: 0 | X14: 0 | Y14: 0 | Z14: 0 | AA14: 0 | AB14: 5095.089 | AC14: 16.58 | AD14: 17.797 | AE14: 6.743 | AF14: 0 | AG14: 41.12 | AH14: 36.305 | AI14: 0 | AJ14: 36.305 | AK14: 0 | AL14: 0 | AM14: 0 | AN14: 1071.915 | AO14: 2692.658 | AP14: 0 | AQ14: 263.468 | AR14: 904.068 | AS14: 72.611 | AT14: 1108.22 | AU14: 0 | AV14: 0 | AW14: 0 | AX14: 0 | AY14: 0 | AZ14: 0 | BA14: 0 | BB14: 0 | BC14: 26326.602
A15: 1980 | B15: 81.741 | C15: 10029.441 | D15: 0 | E15: 500.50686 | F15: 0 | G15: 10611.689 | H15: 6138.302 | I15: 0 | J15: 0 | K15: 0 | L15: 0 | M15: 0 | N15: 0 | O15: 0 | P15: 0 | Q15: 0 | R15: 0 | S15: 0 | T15: 0 | U15: 592.673 | V15: 5085.363 | W15: 0 | X15: 0 | Y15: 0 | Z15: 0 | AA15: 0 | AB15: 5678.036 | AC15: 19.187 | AD15: 19.261 | AE15: 7.452 | AF15: 0 | AG15: 45.9 | AH15: 37.149 | AI15: 0 | AJ15: 37.149 | AK15: 0 | AL15: 0 | AM15: 0 | AN15: 1140.037 | AO15: 2539.9301 | AP15: 0 | AQ15: 277.0263 | AR15: 1154.539 | AS15: 72.358 | AT15: 1177.186 | AU15: 0 | AV15: 0 | AW15: 0 | AX15: 0 | AY15: 0 | AZ15: 0 | BA15: 0 | BB15: 0 | BC15: 28872.152
A16: 1981 | B16: 490.873 | C16: 9727.5609 | D16: 0 | E16: 574.59938 | F16: 0 | G16: 10793.033 | H16: 6567.711 | I16: 0 | J16: 0 | K16: 0 | L16: 0 | M16: 0 | N16: 0 | O16: 0 | P16: 0 | Q16: 0 | R16: 0 | S16: 0 | T16: 0 | U16: 1982.975 | V16: 5483.223 | W16: 0 | X16: 0 | Y16: 0 | Z16: 0 | AA16: 0 | AB16: 7466.198 | AC16: 19.207 | AD16: 22.702 | AE16: 5.786 | AF16: 0 | AG16: 47.695 | AH16: 30.653 | AI16: 0 | AJ16: 30.653 | AK16: 0 | AL16: 0 | AM16: 0 | AN16: 1081.037 | AO16: 2320.6608 | AP16: 0 | AQ16: 339.44879 | AR16: 1295.51 | AS16: 64.588 | AT16: 1111.69 | AU16: 0 | AV16: 0 | AW16: 0 | AX16: 0 | AY16: 0 | AZ16: 0 | BA16: 0 | BB16: 0 | BC16: 31118.225
A17: 1982 | B17: 680.122 | C17: 9599.2133 | D17: 0 | E17: 692.13633 | F17: 0 | G17: 10971.472 | H17: 0 | I17: 0 | J17: 0 | K17: 0 | L17: 6577.763 | M17: 0 | N17: 0 | O17: 0 | P17: 23.457 | Q17: 0 | R17: 0 | S17: 0 | T17: 6601.22 | U17: 0 | V17: 0 | W17: 2155.43 | X17: 4976.901 | Y17: 386.37 | Z17: 0 | AA17: 0 | AB17: 7518.701 | AC17: 23.853 | AD17: 26.875 | AE17: 5.226 | AF17: 0 | AG17: 55.954 | AH17: 31.609 | AI17: 0.262 | AJ17: 31.871 | AK17: 0 | AL17: 0 | AM17: 0 | AN17: 1072.755 | AO17: 2511.8234 | AP17: 0 | AQ17: 315.49928 | AR17: 1459.003 | AS17: 59.878 | AT17: 1104.626 | AU17: 67.443 | AV17: 0 | AW17: 0 | AX17: 0 | AY17: 0 | AZ17: 0 | BA17: 0 | BB17: 0 | BC17: 31770.245
A18: 1983 | B18: 319.52 | C18: 8670.4182 | D18: 0 | E18: 521.775 | F18: 0 | G18: 9511.7132 | H18: 0 | I18: 0 | J18: 0 | K18: 0 | L18: 4851.208 | M18: 0 | N18: 0 | O18: 949.227 | P18: 25.867 | Q18: 0 | R18: 48.18 | S18: 0 | T18: 5874.482 | U18: 0 | V18: 0 | W18: 4739.724 | X18: 2227.969 | Y18: 87.677 | Z18: 0 | AA18: 338.304 | AB18: 7393.674 | AC18: 22.903 | AD18: 25.3 | AE18: 4.645 | AF18: 0 | AG18: 52.848 | AH18: 32.397 | AI18: 0.321 | AJ18: 32.718 | AK18: 0 | AL18: 0 | AM18: 0 | AN18: 912.965 | AO18: 2105.3653 | AP18: 0 | AQ18: 253.38547 | AR18: 1623.702 | AS18: 101.155 | AT18: 945.683 | AU18: 33.837 | AV18: 0 | AW18: 0 | AX18: 0 | AY18: 0 | AZ18: 0 | BA18: 0 | BB18: 0 | BC18: 28841.528
... A48: 2013 | B48: 5170.1751 | C48: 18630.715 | D48: 1126.9861 | E48: 0 | F48: 0 | G48: 24927.876 | H48: 0 | I48: 32.803857 | J48: 31.169682 | K48: 63.973539 | L48: 8222.063 | M48: 19486.936 | N48: 2514.5045 | O48: 1653.1084 | P48: 0 | Q48: 0 | R48: 0 | S48: 0 | T48: 31876.612 | U48: 0 | V48: 0 | W48: 1985.323 | X48: 2754.0633 | Y48: 0 | Z48: 3909.9791 | AA48: 0 | AB48: 8649.3654 | AC48: 78.233333 | AD48: 89.538095 | AE48: 0 | AF48: 0 | AG48: 167.77143 | AH48: 30.16131 | AI48: 0.33780952 | AJ48: 30.499119 | AK48: 1211.6424 | AL48: 1642.6365 | AM48: 2854.2789 | AN48: 0 | AO48: 0 | AP48: 0.71428571 | AQ48: 2365.7299 | AR48: 12164.447 | AS48: 217.1409 | AT48: 0 | AU48: 0 | AV48: 64.485 | AW48: 0 | AX48: 817.92148 | AY48: 0 | AZ48: 0 | BA48: 0 | BB48: 6168.8212 | BC48: 90369.636
A49: 2014 | B49: 5297.4314 | C49: 19303.055 | D49: 1878.8559 | E49: 0 | F49: 0 | G49: 26479.342 | H49: 0 | I49: 28.959048 | J49: 21.758348 | K49: 50.717395 | L49: 8576.634 | M49: 20220.454 | N49: 2861.0895 | O49: 1833.3179 | P49: 0 | Q49: 0 | R49: 0 | S49: 0 | T49: 33491.496 | U49: 0 | V49: 0 | W49: 2021.478 | X49: 3041.9491 | Y49: 0 | Z49: 4069.7585 | AA49: 0 | AB49: 9133.1856 | AC49: 66.2 | AD49: 94.379238 | AE49: 0 | AF49: 0 | AG49: 160.57924 | AH49: 36.917167 | AI49: 0.33780952 | AJ49: 37.254976 | AK49: 1232.63 | AL49: 1593.1133 | AM49: 2825.7433 | AN49: 0 | AO49: 0 | AP49: 0.95238095 | AQ49: 2451.113 | AR49: 12468.432 | AS49: 214.71405 | AT49: 0 | AU49: 0 | AV49: 0 | AW49: 0 | AX49: 863.2264 | AY49: 0 | AZ49: 0 | BB49: 6473.1571 | BC49: 94649.913
A50: 2015 | B50: 5312.3369 | C50: 17638.273 | D50: 4367.3326 | E50: 0 | F50: 0 | G50: 27317.942 | H50: 0 | I50: 24.770714 | J50: 12.043931 | K50: 36.814646 | L50: 7564.3663 | M50: 20412.333 | N50: 3175.0151 | O50: 1904.8156 | P50: 0 | Q50: 0 | R50: 0 | S50: 0 | T50: 33056.53 | U50: 0 | V50: 0 | W50: 1838.6475 | X50: 2406.4758 | Y50: 0 | Z50: 3675.8277 | AA50: 0 | AB50: 7920.9511 | AC50: 60.781405 | AD50: 99.02369 | AE50: 0 | AF50: 0 | AG50: 159.8051 | AH50: 38.152357 | AI50: 0.33780952 | AJ50: 38.490167 | AK50: 1233.9477 | AL50: 1453.755 | AM50: 2687.7027 | AN50: 0 | AO50: 0 | AP50: 0.71428571 | AQ50: 1509.379 | AR50: 12704.981 | AS50: 200.08071 | AT50: 0 | AU50: 0 | AV50: 13.342 | AW50: 0 | AX50: 856.2226 | AY50: 0 | AZ50: 0 | BB50: 6298.3207 | BC50: 92801.276
A51: 2016 | B51: 4645.6132 | C51: 17767.008 | D51: 5152.6538 | E51: 0 | F51: 0 | G51: 27565.275 | H51: 0 | I51: 19.96731 | J51: 2.7997238 | K51: 22.767033 | L51: 6982.9207 | M51: 20015.508 | N51: 2291.8062 | O51: 1889.2475 | P51: 0 | Q51: 0 | R51: 0 | S51: 0 | T51: 31179.483 | U51: 0 | V51: 0 | W51: 2163.3635 | X51: 2083.0362 | Y51: 0 | Z51: 2951.1914 | AA51: 0 | AB51: 7197.5911 | AC51: 53.329143 | AD51: 89.691548 | AE51: 0 | AF51: 0 | AG51: 143.02069 | AH51: 34.044286 | AI51: 0.33780952 | AJ51: 34.382095 | AK51: 731.24826 | AL51: 1814.6003 | AM51: 2545.8486 | AN51: 0 | AO51: 0 | AP51: 0.4713 | AQ51: 1449.6283 | AR51: 12440.746 | AS51: 77.525976 | AT51: 0 | AU51: 0 | AV51: 25.183571 | AW51: 0 | AX51: 777.30667 | AY51: 0 | AZ51: 0 | BB51: 4164.0706 | BC51: 87623.299
A55: Notas
A56: regresar al índice
